Workbook

Sheet Disclaimer
B2: FLOORLINE · Multi-Account Tracker
B3: Read this first.
B5: DISCLAIMER
B6: Not financial, trading, or investment advice; educational calculation tool only.
B7: Not affiliated with, endorsed by, or sponsored by any prop firm, exchange (CME Group), or platform named.
B8: Prop firm rules change without notice. Every preset shows source_url, checked_date (2026-10-14 for v0.1) and page date; verify against the firm's current rules and your dashboard before trading. Presets are not guaranteed permanent or complete; "partial" presets require user input.
B9: The tracker relies on user-entered balances; it cannot see intraday order of events and can differ from the firm's real-time system. The firm's own calculation is authoritative.
B10: Spreadsheet floating-point arithmetic; values are rounded to cents conservatively.
B12: Spec: tracker v0.1.0 / oracle v0.2.0. No macros, no scripts, no external links or data connections.

Sheet How to use
B2: How to use
B3: REQUIREMENTS
B4: Microsoft Excel 2019, Excel 2021 or Microsoft 365 (uses MAXIFS and TEXTJOIN; Excel 2016 and earlier show #NAME? and are NOT supported).
B5: Tested: formulas were recalculated and checked in LibreOffice only. Excel and Google Sheets have NOT been tested; treat both as unverified until you confirm the results yourself.
B6: GOOGLE SHEETS IMPORT (UNTESTED)
B7: 1. Open drive.google.com, click New > File upload and choose Floorline-Tracker.xlsx.
B8: 2. Right-click the uploaded file > Open with > Google Sheets (or set Drive Settings > 'Convert uploads' before uploading).
B9: 3. In Sheets: File > Save as Google Sheets if it opened in Office-compatibility mode, then work in the converted copy.
B10: 4. Check the Accounts tab: Check column shows OK for filled rows and no cell shows #NAME? or #ERROR!. Compare a few results with your firm dashboard before relying on it.
B11: 5. Not verified in Sheets: whether sheet protection, dropdowns, data validation and colour rules survive the import. Pasted values can bypass dropdowns and validation; the formulas check many inputs, but not every possible mistake.
B12: DAILY ROUTINE
B13: 1. Accounts: one row per account (max 10). Enter Account ID and pick a Preset (or Manual). Read the Flags column.
... B26: Matching ignores letter case: account IDs must be unique ignoring case (p16 and P16 are duplicates), log row p16 belongs to account P16, and none / None count as NONE. Spaces are NOT ignored: 'Static ' with a trailing space is INVALID.

Sheet Accounts
A1: Account ID | B1: Preset | C1: Preset status | D1: Type override | E1: Start override | F1: DD $ override | G1: Lock offset override | H1: Touch = breach override | I1: DLL $ override | J1: Max contracts override | K1: Equity now (incl. open P&L) | L1: Day reference balance | M1: Risk $ / trade | N1: Stop ticks | O1: Tick value $ | P1: Type | Q1: Start | R1: Max DD $ | S1: Lock offset | T1: Touch = breach | U1: DLL $ | V1: Max contracts | W1: Check | X1: Peak | Y1: FLOOR | Z1: Locked | AA1: Breached | AB1: DD room | AC1: Daily room | AD1: BINDING ROOM | AE1: Binding | AF1: Effective risk | AG1: CONTRACTS | AH1: Capped | AI1: Room-limited | AJ1: floor raw | AK1: sizing check | AL1: contracts raw | AM1: Actual risk | AN1: Flags
C2: =IFERROR(INDEX(Presets!$B$2:$B$200,MATCH($B2,Presets!$A$2:$A$200,0))&"","") | P2: =IFERROR(IF(D2<>"",D2,IFERROR(INDEX(Presets!$C$2:$C$200,MATCH($B2,Presets!$A$2:$A$200,0))&"","")),"INVALID") | Q2: =IFERROR(IF(E2<>"",E2,IF(IFERROR(INDEX(Presets!$D$2:$D$200,MATCH($B2,Presets!$A$2:$A$200,0))&"","")<>"",VALUE(IFERROR(INDEX(Presets!$D$2:$D$200,MATCH($B2,Presets!$A$2:$A$200,0))&"","")),"")),"INVALID") | R2: =IFERROR(IF(F2<>"",F2,IF(IFERROR(INDEX(Presets!$E$2:$E$200,MATCH($B2,Presets!$A$2:$A$200,0))&"","")<>"",VALUE(IFERROR(INDEX(Presets!$E$2:$E$200,MATCH($B2,Presets!$A$2:$A$200,0))&"","")),IF(AND(IFERROR(INDEX(Presets!$F$2:$F$200,MATCH($B2,Presets!$A$2:$A$200,0))&"","")<>"",ISNUMBER(Q2)),VALUE(IFERROR(INDEX(Presets!$F$2:$F$200,MATCH($B2,Presets!$A$2:$A$200,0))&"",""))/100*Q2,""))),"INVALID") | S2: =IFERROR(IF(G2<>"",G2,IF(IFERROR(INDEX(Presets!$G$2:$G$200,MATCH($B2,Presets!$A$2:$A$200,0))&"","")="NONE","NONE",IF(IFERROR(INDEX(Presets!$G$2:$G$200,MATCH($B2,Presets!$A$2:$A$200,0))&"","")<>"",VALUE(IFERROR(INDEX(Presets!$G$2:$G$200,MATCH($B2,Presets!$A$2:$A$200,0))&"","")),""))),"INVALID") | T2: =IFERROR(IF(H2<>"",H2,IF(IFERROR(INDEX(Presets!$H$2:$H$200,MATCH($B2,Presets!$A$2:$A$200,0))&"","")="TRUE",TRUE,IF(IFERROR(INDEX(Presets!$H$2:$H$200,MATCH($B2,Presets!$A$2:$A$200,0))&"","")="FALSE",FALSE,""))),"INVALID") | U2: =IFERROR(IF(I2<>"",I2,IF(IFERROR(INDEX(Presets!$I$2:$I$200,MATCH($B2,Presets!$A$2:$A$200,0))&"","")="NONE","NONE",IF(IFERROR(INDEX(Presets!$I$2:$I$200,MATCH($B2,Presets!$A$2:$A$200,0))&"","")<>"",VALUE(IFERROR(INDEX(Presets!$I$2:$I$200,MATCH($B2,Presets!$A$2:$A$200,0))&"","")),""))),"INVALID") | V2: =IFERROR(IF(J2<>"",J2,IF(IFERROR(INDEX(Presets!$J$2:$J$200,MATCH($B2,Presets!$A$2:$A$200,0))&"","")<>"",VALUE(IFERROR(INDEX(Presets!$J$2:$J$200,MATCH($B2,Presets!$A$2:$A$200,0))&"","")),"")),"INVALID") | W2: =IFERROR(IF(AND(A2="",B2=""),"",IF(OR(A2="",B2="",P2="",Q2="",R2="",S2="",T2="",U2="",V2="",K2="",AND(U2<>"NONE",L2="")),"INCOMPLETE",IF(OR(COUNTIFS($A$2:$A$11,A2)>1,AND(P2<>"static",P2<>"eod_trailing",P2<>"intraday_trailing"),NOT(ISNUMBER(Q2)),Q2<=0,ROUND(Q2*100,6)<>INT(ROUND(Q2*100,6)),NOT(ISNUMBER(R2)),R2<=0,ROUND(R2*100,6)<>INT(ROUND(R2*100,6)),AND(S2<>"NONE",NOT(ISNUMBER(S2))),AND(P2="static",S2<>"NONE"),IF(ISNUMBER(S2),ROUND(Q2+S2-(Q2-R2),6)<=0,FALSE),IF(ISNUMBER(S2),OR(S2<-100000000,S2>100000000),FALSE),AND(T2<>TRUE,T2<>FALSE),AND(U2<>"NONE",OR(NOT(ISNUMBER(U2)),U2<=0)),IF(V2="NONE",FALSE,IF(ISNUMBER(V2),OR(V2<0,V2<>INT(V2)),TRUE)),NOT(ISNUMBER(K2)),AND(U2<>"NONE",NOT(ISNUMBER(L2))),Q2>100000000,R2>100000000,K2<=0,K2>100000000,IF(ISNUMBER(U2),U2>100000000,FALSE),IF(ISNUMBER(L2),OR(L2<=0,L2>100000000),FALSE)),"INVALID",IF(COUNTIFS('Daily Log'!$A$2:$A$1001,A2,'Daily Log'!$I$2:$I$1001,"INVALID")>0,"INVALID",IF(OR(COUNTIFS('Daily Log'!$A$2:$A$1001,A2,'Daily Log'!$I$2:$I$1001,"INCOMPLETE")>0,COUNTIFS('Daily Log'!$I$2:$I$1001,"UNKNOWN_ACCOUNT")>0),"INCOMPLETE","OK"))))),"INVALID") | X2: =IFERROR(IF($W2<>"OK",$W2,IF(P2="static",Q2,IF(P2="eod_trailing",MAX(Q2,_xlfn.MAXIFS('Daily Log'!$C$2:$C$1001,'Daily Log'!$A$2:$A$1001,A2)),MAX(Q2,K2,_xlfn.MAXIFS('Daily Log'!$C$2:$C$1001,'Daily Log'!$A$2:$A$1001,A2),_xlfn.MAXIFS('Daily Log'!$D$2:$D$1001,'Daily Log'!$A$2:$A$1001,A2))))),"INVALID") | Y2: =IFERROR(IF($W2<>"OK",$W2,-INT(ROUND(-(AJ2)*100,6))/100),"INVALID") | Z2: =IFERROR(IF($W2<>"OK",$W2,AND(ISNUMBER(S2),P2<>"static",ROUND(X2-R2-(Q2+IF(ISNUMBER(S2),S2,0)),6)>=0)),"INVALID") | AA2: =IFERROR(IF($W2<>"OK",$W2,OR(COUNTIFS('Daily Log'!$A$2:$A$1001,A2,'Daily Log'!$I$2:$I$1001,"BREACHED")>0,IF(T2,ROUND(K2-(AJ2),6)<=0,ROUND(K2-(AJ2),6)<0))),"INVALID") | AB2: =IFERROR(IF($W2<>"OK",$W2,IF(AA2,"BREACHED",INT(ROUND((MAX(0,K2-AJ2))*100,6))/100)),"INVALID") | AC2: =IFERROR(IF($W2<>"OK",$W2,IF(AA2,"BREACHED",IF(U2="NONE","NONE",INT(ROUND((MAX(0,U2-MAX(0,-(K2-L2))))*100,6))/100))),"INVALID") | AD2: =IFERROR(IF($W2<>"OK",$W2,IF(AA2,"BREACHED",IF(AC2="NONE",AB2,MIN(AB2,AC2)))),"INVALID") | AE2: =IFERROR(IF($W2<>"OK",$W2,IF(AA2,"BREACHED",IF(AND(AC2<>"NONE",AC2<AB2),"daily_loss","drawdown"))),"INVALID") | AF2: =IFERROR(IF(AK2<>"OK",AK2,IF(AA2,"BREACHED",INT(ROUND((MIN(M2,AD2))*100,6))/100)),"INVALID") | AG2: =IFERROR(IF(AK2<>"OK",AK2,IF(AA2,"BREACHED",IF(V2="NONE",AL2,MIN(AL2,V2)))),"INVALID") | AH2: =IFERROR(IF(AK2<>"OK",AK2,AND(V2<>"NONE",AL2>V2)),"INVALID") | AI2: =IFERROR(IF(AK2<>"OK",AK2,M2>AD2),"INVALID") | AJ2: =IFERROR(IF($W2<>"OK","",IF(P2="static",Q2-R2,IF(S2="NONE",X2-R2,MIN(X2-R2,Q2+S2)))),"INVALID") | AK2: =IFERROR(IF($W2<>"OK",$W2,IF(OR(M2="",N2="",O2=""),"INCOMPLETE",IF(OR(NOT(ISNUMBER(M2)),M2<0,NOT(ISNUMBER(N2)),N2<1,N2<>INT(N2),NOT(ISNUMBER(O2)),O2<=0,O2>100000,ROUND(O2*1000000,3)<>INT(ROUND(O2*1000000,3)),M2>100000000),"INVALID","OK"))),"INVALID") | AL2: =IFERROR(IF(AK2<>"OK","",IF(AA2,0,INT(ROUND(MIN(M2,AD2)/(N2*O2),9)))),"INVALID") | AM2: =IFERROR(IF(AK2<>"OK",AK2,IF(AA2,"BREACHED",INT(ROUND((AG2*N2*O2)*100,6))/100)),"INVALID") | AN2: =IFERROR(IF(AND(A2="",B2=""),"",_xlfn.TEXTJOIN("; ",TRUE,IF(C2="partial","PARTIAL PRESET: verify "&IFERROR(INDEX(Presets!$L$2:$L$200,MATCH($B2,Presets!$A$2:$A$200,0))&"",""),""),IF(C2="manual","MANUAL: all params user-entered",""),IF(OR(AND(D2<>"",IFERROR(INDEX(Presets!$C$2:$C$200,MATCH($B2,Presets!$A$2:$A$200,0))&"","")<>""),AND(E2<>"",IFERROR(INDEX(Presets!$D$2:$D$200,MATCH($B2,Presets!$A$2:$A$200,0))&"","")<>""),AND(F2<>"",IFERROR(INDEX(Presets!$E$2:$E$200,MATCH($B2,Presets!$A$2:$A$200,0))&"","")<>""),AND(G2<>"",IFERROR(INDEX(Presets!$G$2:$G$200,MATCH($B2,Presets!$A$2:$A$200,0))&"","")<>""),AND(H2<>"",IFERROR(INDEX(Presets!$H$2:$H$200,MATCH($B2,Presets!$A$2:$A$200,0))&"","")<>""),AND(I2<>"",IFERROR(INDEX(Presets!$I$2:$I$200,MATCH($B2,Presets!$A$2:$A$200,0))&"","")<>""),AND(J2<>"",IFERROR(INDEX(Presets!$J$2:$J$200,MATCH($B2,Presets!$A$2:$A$200,0))&"","")<>"")),"OVERRIDES PRESET",""),IF(AND(A2<>"",V2=""),"MAX CONTRACTS MISSING: enter a number or NONE",""),IF(AND(IFERROR(INDEX(Presets!$N$2:$N$200,MATCH($B2,Presets!$A$2:$A$200,0))&"","")<>"",NOT(ISNUMBER($B$13))),"AS-OF DATE MISSING: enter today in B13 (stale check off)",""),IF(AND(IFERROR(INDEX(Presets!$N$2:$N$200,MATCH($B2,Presets!$A$2:$A$200,0))&"","")<>"",ISNUMBER($B$13)),IF($B$13-DATE(VALUE(LEFT(IFERROR(INDEX(Presets!$N$2:$N$200,MATCH($B2,Presets!$A$2:$A$200,0))&"",""),4)),VALUE(MID(IFERROR(INDEX(Presets!$N$2:$N$200,MATCH($B2,Presets!$A$2:$A$200,0))&"",""),6,2)),VALUE(MID(IFERROR(INDEX(Presets!$N$2:$N$200,MATCH($B2,Presets!$A$2:$A$200,0))&"",""),9,2)))>30,"STALE PRESET: checked "&IFERROR(INDEX(Presets!$N$2:$N$200,MATCH($B2,Presets!$A$2:$A$200,0))&"","")&", over 30 days before As of",""),""),IF(IFERROR(INDEX(Presets!$M$2:$M$200,MATCH($B2,Presets!$A$2:$A$200,0))&"","")<>"","source: "&IFERROR(INDEX(Presets!$M$2:$M$200,MATCH($B2,Presets!$A$2:$A$200,0))&"","")&" checked "&IFERROR(INDEX(Presets!$N$2:$N$200,MATCH($B2,Presets!$A$2:$A$200,0))&"",""),""))),"INVALID")
C3: =IFERROR(INDEX(Presets!$B$2:$B$200,MATCH($B3,Presets!$A$2:$A$200,0))&"","") | P3: =IFERROR(IF(D3<>"",D3,IFERROR(INDEX(Presets!$C$2:$C$200,MATCH($B3,Presets!$A$2:$A$200,0))&"","")),"INVALID") | Q3: =IFERROR(IF(E3<>"",E3,IF(IFERROR(INDEX(Presets!$D$2:$D$200,MATCH($B3,Presets!$A$2:$A$200,0))&"","")<>"",VALUE(IFERROR(INDEX(Presets!$D$2:$D$200,MATCH($B3,Presets!$A$2:$A$200,0))&"","")),"")),"INVALID") | R3: =IFERROR(IF(F3<>"",F3,IF(IFERROR(INDEX(Presets!$E$2:$E$200,MATCH($B3,Presets!$A$2:$A$200,0))&"","")<>"",VALUE(IFERROR(INDEX(Presets!$E$2:$E$200,MATCH($B3,Presets!$A$2:$A$200,0))&"","")),IF(AND(IFERROR(INDEX(Presets!$F$2:$F$200,MATCH($B3,Presets!$A$2:$A$200,0))&"","")<>"",ISNUMBER(Q3)),VALUE(IFERROR(INDEX(Presets!$F$2:$F$200,MATCH($B3,Presets!$A$2:$A$200,0))&"",""))/100*Q3,""))),"INVALID") | S3: =IFERROR(IF(G3<>"",G3,IF(IFERROR(INDEX(Presets!$G$2:$G$200,MATCH($B3,Presets!$A$2:$A$200,0))&"","")="NONE","NONE",IF(IFERROR(INDEX(Presets!$G$2:$G$200,MATCH($B3,Presets!$A$2:$A$200,0))&"","")<>"",VALUE(IFERROR(INDEX(Presets!$G$2:$G$200,MATCH($B3,Presets!$A$2:$A$200,0))&"","")),""))),"INVALID") | T3: =IFERROR(IF(H3<>"",H3,IF(IFERROR(INDEX(Presets!$H$2:$H$200,MATCH($B3,Presets!$A$2:$A$200,0))&"","")="TRUE",TRUE,IF(IFERROR(INDEX(Presets!$H$2:$H$200,MATCH($B3,Presets!$A$2:$A$200,0))&"","")="FALSE",FALSE,""))),"INVALID") | U3: =IFERROR(IF(I3<>"",I3,IF(IFERROR(INDEX(Presets!$I$2:$I$200,MATCH($B3,Presets!$A$2:$A$200,0))&"","")="NONE","NONE",IF(IFERROR(INDEX(Presets!$I$2:$I$200,MATCH($B3,Presets!$A$2:$A$200,0))&"","")<>"",VALUE(IFERROR(INDEX(Presets!$I$2:$I$200,MATCH($B3,Presets!$A$2:$A$200,0))&"","")),""))),"INVALID") | V3: =IFERROR(IF(J3<>"",J3,IF(IFERROR(INDEX(Presets!$J$2:$J$200,MATCH($B3,Presets!$A$2:$A$200,0))&"","")<>"",VALUE(IFERROR(INDEX(Presets!$J$2:$J$200,MATCH($B3,Presets!$A$2:$A$200,0))&"","")),"")),"INVALID") | W3: =IFERROR(IF(AND(A3="",B3=""),"",IF(OR(A3="",B3="",P3="",Q3="",R3="",S3="",T3="",U3="",V3="",K3="",AND(U3<>"NONE",L3="")),"INCOMPLETE",IF(OR(COUNTIFS($A$2:$A$11,A3)>1,AND(P3<>"static",P3<>"eod_trailing",P3<>"intraday_trailing"),NOT(ISNUMBER(Q3)),Q3<=0,ROUND(Q3*100,6)<>INT(ROUND(Q3*100,6)),NOT(ISNUMBER(R3)),R3<=0,ROUND(R3*100,6)<>INT(ROUND(R3*100,6)),AND(S3<>"NONE",NOT(ISNUMBER(S3))),AND(P3="static",S3<>"NONE"),IF(ISNUMBER(S3),ROUND(Q3+S3-(Q3-R3),6)<=0,FALSE),IF(ISNUMBER(S3),OR(S3<-100000000,S3>100000000),FALSE),AND(T3<>TRUE,T3<>FALSE),AND(U3<>"NONE",OR(NOT(ISNUMBER(U3)),U3<=0)),IF(V3="NONE",FALSE,IF(ISNUMBER(V3),OR(V3<0,V3<>INT(V3)),TRUE)),NOT(ISNUMBER(K3)),AND(U3<>"NONE",NOT(ISNUMBER(L3))),Q3>100000000,R3>100000000,K3<=0,K3>100000000,IF(ISNUMBER(U3),U3>100000000,FALSE),IF(ISNUMBER(L3),OR(L3<=0,L3>100000000),FALSE)),"INVALID",IF(COUNTIFS('Daily Log'!$A$2:$A$1001,A3,'Daily Log'!$I$2:$I$1001,"INVALID")>0,"INVALID",IF(OR(COUNTIFS('Daily Log'!$A$2:$A$1001,A3,'Daily Log'!$I$2:$I$1001,"INCOMPLETE")>0,COUNTIFS('Daily Log'!$I$2:$I$1001,"UNKNOWN_ACCOUNT")>0),"INCOMPLETE","OK"))))),"INVALID") | X3: =IFERROR(IF($W3<>"OK",$W3,IF(P3="static",Q3,IF(P3="eod_trailing",MAX(Q3,_xlfn.MAXIFS('Daily Log'!$C$2:$C$1001,'Daily Log'!$A$2:$A$1001,A3)),MAX(Q3,K3,_xlfn.MAXIFS('Daily Log'!$C$2:$C$1001,'Daily Log'!$A$2:$A$1001,A3),_xlfn.MAXIFS('Daily Log'!$D$2:$D$1001,'Daily Log'!$A$2:$A$1001,A3))))),"INVALID") | Y3: =IFERROR(IF($W3<>"OK",$W3,-INT(ROUND(-(AJ3)*100,6))/100),"INVALID") | Z3: =IFERROR(IF($W3<>"OK",$W3,AND(ISNUMBER(S3),P3<>"static",ROUND(X3-R3-(Q3+IF(ISNUMBER(S3),S3,0)),6)>=0)),"INVALID") | AA3: =IFERROR(IF($W3<>"OK",$W3,OR(COUNTIFS('Daily Log'!$A$2:$A$1001,A3,'Daily Log'!$I$2:$I$1001,"BREACHED")>0,IF(T3,ROUND(K3-(AJ3),6)<=0,ROUND(K3-(AJ3),6)<0))),"INVALID") | AB3: =IFERROR(IF($W3<>"OK",$W3,IF(AA3,"BREACHED",INT(ROUND((MAX(0,K3-AJ3))*100,6))/100)),"INVALID") | AC3: =IFERROR(IF($W3<>"OK",$W3,IF(AA3,"BREACHED",IF(U3="NONE","NONE",INT(ROUND((MAX(0,U3-MAX(0,-(K3-L3))))*100,6))/100))),"INVALID") | AD3: =IFERROR(IF($W3<>"OK",$W3,IF(AA3,"BREACHED",IF(AC3="NONE",AB3,MIN(AB3,AC3)))),"INVALID") | AE3: =IFERROR(IF($W3<>"OK",$W3,IF(AA3,"BREACHED",IF(AND(AC3<>"NONE",AC3<AB3),"daily_loss","drawdown"))),"INVALID") | AF3: =IFERROR(IF(AK3<>"OK",AK3,IF(AA3,"BREACHED",INT(ROUND((MIN(M3,AD3))*100,6))/100)),"INVALID") | AG3: =IFERROR(IF(AK3<>"OK",AK3,IF(AA3,"BREACHED",IF(V3="NONE",AL3,MIN(AL3,V3)))),"INVALID") | AH3: =IFERROR(IF(AK3<>"OK",AK3,AND(V3<>"NONE",AL3>V3)),"INVALID") | AI3: =IFERROR(IF(AK3<>"OK",AK3,M3>AD3),"INVALID") | AJ3: =IFERROR(IF($W3<>"OK","",IF(P3="static",Q3-R3,IF(S3="NONE",X3-R3,MIN(X3-R3,Q3+S3)))),"INVALID") | AK3: =IFERROR(IF($W3<>"OK",$W3,IF(OR(M3="",N3="",O3=""),"INCOMPLETE",IF(OR(NOT(ISNUMBER(M3)),M3<0,NOT(ISNUMBER(N3)),N3<1,N3<>INT(N3),NOT(ISNUMBER(O3)),O3<=0,O3>100000,ROUND(O3*1000000,3)<>INT(ROUND(O3*1000000,3)),M3>100000000),"INVALID","OK"))),"INVALID") | AL3: =IFERROR(IF(AK3<>"OK","",IF(AA3,0,INT(ROUND(MIN(M3,AD3)/(N3*O3),9)))),"INVALID") | AM3: =IFERROR(IF(AK3<>"OK",AK3,IF(AA3,"BREACHED",INT(ROUND((AG3*N3*O3)*100,6))/100)),"INVALID") | AN3: =IFERROR(IF(AND(A3="",B3=""),"",_xlfn.TEXTJOIN("; ",TRUE,IF(C3="partial","PARTIAL PRESET: verify "&IFERROR(INDEX(Presets!$L$2:$L$200,MATCH($B3,Presets!$A$2:$A$200,0))&"",""),""),IF(C3="manual","MANUAL: all params user-entered",""),IF(OR(AND(D3<>"",IFERROR(INDEX(Presets!$C$2:$C$200,MATCH($B3,Presets!$A$2:$A$200,0))&"","")<>""),AND(E3<>"",IFERROR(INDEX(Presets!$D$2:$D$200,MATCH($B3,Presets!$A$2:$A$200,0))&"","")<>""),AND(F3<>"",IFERROR(INDEX(Presets!$E$2:$E$200,MATCH($B3,Presets!$A$2:$A$200,0))&"","")<>""),AND(G3<>"",IFERROR(INDEX(Presets!$G$2:$G$200,MATCH($B3,Presets!$A$2:$A$200,0))&"","")<>""),AND(H3<>"",IFERROR(INDEX(Presets!$H$2:$H$200,MATCH($B3,Presets!$A$2:$A$200,0))&"","")<>""),AND(I3<>"",IFERROR(INDEX(Presets!$I$2:$I$200,MATCH($B3,Presets!$A$2:$A$200,0))&"","")<>""),AND(J3<>"",IFERROR(INDEX(Presets!$J$2:$J$200,MATCH($B3,Presets!$A$2:$A$200,0))&"","")<>"")),"OVERRIDES PRESET",""),IF(AND(A3<>"",V3=""),"MAX CONTRACTS MISSING: enter a number or NONE",""),IF(AND(IFERROR(INDEX(Presets!$N$2:$N$200,MATCH($B3,Presets!$A$2:$A$200,0))&"","")<>"",NOT(ISNUMBER($B$13))),"AS-OF DATE MISSING: enter today in B13 (stale check off)",""),IF(AND(IFERROR(INDEX(Presets!$N$2:$N$200,MATCH($B3,Presets!$A$2:$A$200,0))&"","")<>"",ISNUMBER($B$13)),IF($B$13-DATE(VALUE(LEFT(IFERROR(INDEX(Presets!$N$2:$N$200,MATCH($B3,Presets!$A$2:$A$200,0))&"",""),4)),VALUE(MID(IFERROR(INDEX(Presets!$N$2:$N$200,MATCH($B3,Presets!$A$2:$A$200,0))&"",""),6,2)),VALUE(MID(IFERROR(INDEX(Presets!$N$2:$N$200,MATCH($B3,Presets!$A$2:$A$200,0))&"",""),9,2)))>30,"STALE PRESET: checked "&IFERROR(INDEX(Presets!$N$2:$N$200,MATCH($B3,Presets!$A$2:$A$200,0))&"","")&", over 30 days before As of",""),""),IF(IFERROR(INDEX(Presets!$M$2:$M$200,MATCH($B3,Presets!$A$2:$A$200,0))&"","")<>"","source: "&IFERROR(INDEX(Presets!$M$2:$M$200,MATCH($B3,Presets!$A$2:$A$200,0))&"","")&" checked "&IFERROR(INDEX(Presets!$N$2:$N$200,MATCH($B3,Presets!$A$2:$A$200,0))&"",""),""))),"INVALID")
C4: =IFERROR(INDEX(Presets!$B$2:$B$200,MATCH($B4,Presets!$A$2:$A$200,0))&"","") | P4: =IFERROR(IF(D4<>"",D4,IFERROR(INDEX(Presets!$C$2:$C$200,MATCH($B4,Presets!$A$2:$A$200,0))&"","")),"INVALID") | Q4: =IFERROR(IF(E4<>"",E4,IF(IFERROR(INDEX(Presets!$D$2:$D$200,MATCH($B4,Presets!$A$2:$A$200,0))&"","")<>"",VALUE(IFERROR(INDEX(Presets!$D$2:$D$200,MATCH($B4,Presets!$A$2:$A$200,0))&"","")),"")),"INVALID") | R4: =IFERROR(IF(F4<>"",F4,IF(IFERROR(INDEX(Presets!$E$2:$E$200,MATCH($B4,Presets!$A$2:$A$200,0))&"","")<>"",VALUE(IFERROR(INDEX(Presets!$E$2:$E$200,MATCH($B4,Presets!$A$2:$A$200,0))&"","")),IF(AND(IFERROR(INDEX(Presets!$F$2:$F$200,MATCH($B4,Presets!$A$2:$A$200,0))&"","")<>"",ISNUMBER(Q4)),VALUE(IFERROR(INDEX(Presets!$F$2:$F$200,MATCH($B4,Presets!$A$2:$A$200,0))&"",""))/100*Q4,""))),"INVALID") | S4: =IFERROR(IF(G4<>"",G4,IF(IFERROR(INDEX(Presets!$G$2:$G$200,MATCH($B4,Presets!$A$2:$A$200,0))&"","")="NONE","NONE",IF(IFERROR(INDEX(Presets!$G$2:$G$200,MATCH($B4,Presets!$A$2:$A$200,0))&"","")<>"",VALUE(IFERROR(INDEX(Presets!$G$2:$G$200,MATCH($B4,Presets!$A$2:$A$200,0))&"","")),""))),"INVALID") | T4: =IFERROR(IF(H4<>"",H4,IF(IFERROR(INDEX(Presets!$H$2:$H$200,MATCH($B4,Presets!$A$2:$A$200,0))&"","")="TRUE",TRUE,IF(IFERROR(INDEX(Presets!$H$2:$H$200,MATCH($B4,Presets!$A$2:$A$200,0))&"","")="FALSE",FALSE,""))),"INVALID") | U4: =IFERROR(IF(I4<>"",I4,IF(IFERROR(INDEX(Presets!$I$2:$I$200,MATCH($B4,Presets!$A$2:$A$200,0))&"","")="NONE","NONE",IF(IFERROR(INDEX(Presets!$I$2:$I$200,MATCH($B4,Presets!$A$2:$A$200,0))&"","")<>"",VALUE(IFERROR(INDEX(Presets!$I$2:$I$200,MATCH($B4,Presets!$A$2:$A$200,0))&"","")),""))),"INVALID") | V4: =IFERROR(IF(J4<>"",J4,IF(IFERROR(INDEX(Presets!$J$2:$J$200,MATCH($B4,Presets!$A$2:$A$200,0))&"","")<>"",VALUE(IFERROR(INDEX(Presets!$J$2:$J$200,MATCH($B4,Presets!$A$2:$A$200,0))&"","")),"")),"INVALID") | W4: =IFERROR(IF(AND(A4="",B4=""),"",IF(OR(A4="",B4="",P4="",Q4="",R4="",S4="",T4="",U4="",V4="",K4="",AND(U4<>"NONE",L4="")),"INCOMPLETE",IF(OR(COUNTIFS($A$2:$A$11,A4)>1,AND(P4<>"static",P4<>"eod_trailing",P4<>"intraday_trailing"),NOT(ISNUMBER(Q4)),Q4<=0,ROUND(Q4*100,6)<>INT(ROUND(Q4*100,6)),NOT(ISNUMBER(R4)),R4<=0,ROUND(R4*100,6)<>INT(ROUND(R4*100,6)),AND(S4<>"NONE",NOT(ISNUMBER(S4))),AND(P4="static",S4<>"NONE"),IF(ISNUMBER(S4),ROUND(Q4+S4-(Q4-R4),6)<=0,FALSE),IF(ISNUMBER(S4),OR(S4<-100000000,S4>100000000),FALSE),AND(T4<>TRUE,T4<>FALSE),AND(U4<>"NONE",OR(NOT(ISNUMBER(U4)),U4<=0)),IF(V4="NONE",FALSE,IF(ISNUMBER(V4),OR(V4<0,V4<>INT(V4)),TRUE)),NOT(ISNUMBER(K4)),AND(U4<>"NONE",NOT(ISNUMBER(L4))),Q4>100000000,R4>100000000,K4<=0,K4>100000000,IF(ISNUMBER(U4),U4>100000000,FALSE),IF(ISNUMBER(L4),OR(L4<=0,L4>100000000),FALSE)),"INVALID",IF(COUNTIFS('Daily Log'!$A$2:$A$1001,A4,'Daily Log'!$I$2:$I$1001,"INVALID")>0,"INVALID",IF(OR(COUNTIFS('Daily Log'!$A$2:$A$1001,A4,'Daily Log'!$I$2:$I$1001,"INCOMPLETE")>0,COUNTIFS('Daily Log'!$I$2:$I$1001,"UNKNOWN_ACCOUNT")>0),"INCOMPLETE","OK"))))),"INVALID") | X4: =IFERROR(IF($W4<>"OK",$W4,IF(P4="static",Q4,IF(P4="eod_trailing",MAX(Q4,_xlfn.MAXIFS('Daily Log'!$C$2:$C$1001,'Daily Log'!$A$2:$A$1001,A4)),MAX(Q4,K4,_xlfn.MAXIFS('Daily Log'!$C$2:$C$1001,'Daily Log'!$A$2:$A$1001,A4),_xlfn.MAXIFS('Daily Log'!$D$2:$D$1001,'Daily Log'!$A$2:$A$1001,A4))))),"INVALID") | Y4: =IFERROR(IF($W4<>"OK",$W4,-INT(ROUND(-(AJ4)*100,6))/100),"INVALID") | Z4: =IFERROR(IF($W4<>"OK",$W4,AND(ISNUMBER(S4),P4<>"static",ROUND(X4-R4-(Q4+IF(ISNUMBER(S4),S4,0)),6)>=0)),"INVALID") | AA4: =IFERROR(IF($W4<>"OK",$W4,OR(COUNTIFS('Daily Log'!$A$2:$A$1001,A4,'Daily Log'!$I$2:$I$1001,"BREACHED")>0,IF(T4,ROUND(K4-(AJ4),6)<=0,ROUND(K4-(AJ4),6)<0))),"INVALID") | AB4: =IFERROR(IF($W4<>"OK",$W4,IF(AA4,"BREACHED",INT(ROUND((MAX(0,K4-AJ4))*100,6))/100)),"INVALID") | AC4: =IFERROR(IF($W4<>"OK",$W4,IF(AA4,"BREACHED",IF(U4="NONE","NONE",INT(ROUND((MAX(0,U4-MAX(0,-(K4-L4))))*100,6))/100))),"INVALID") | AD4: =IFERROR(IF($W4<>"OK",$W4,IF(AA4,"BREACHED",IF(AC4="NONE",AB4,MIN(AB4,AC4)))),"INVALID") | AE4: =IFERROR(IF($W4<>"OK",$W4,IF(AA4,"BREACHED",IF(AND(AC4<>"NONE",AC4<AB4),"daily_loss","drawdown"))),"INVALID") | AF4: =IFERROR(IF(AK4<>"OK",AK4,IF(AA4,"BREACHED",INT(ROUND((MIN(M4,AD4))*100,6))/100)),"INVALID") | AG4: =IFERROR(IF(AK4<>"OK",AK4,IF(AA4,"BREACHED",IF(V4="NONE",AL4,MIN(AL4,V4)))),"INVALID") | AH4: =IFERROR(IF(AK4<>"OK",AK4,AND(V4<>"NONE",AL4>V4)),"INVALID") | AI4: =IFERROR(IF(AK4<>"OK",AK4,M4>AD4),"INVALID") | AJ4: =IFERROR(IF($W4<>"OK","",IF(P4="static",Q4-R4,IF(S4="NONE",X4-R4,MIN(X4-R4,Q4+S4)))),"INVALID") | AK4: =IFERROR(IF($W4<>"OK",$W4,IF(OR(M4="",N4="",O4=""),"INCOMPLETE",IF(OR(NOT(ISNUMBER(M4)),M4<0,NOT(ISNUMBER(N4)),N4<1,N4<>INT(N4),NOT(ISNUMBER(O4)),O4<=0,O4>100000,ROUND(O4*1000000,3)<>INT(ROUND(O4*1000000,3)),M4>100000000),"INVALID","OK"))),"INVALID") | AL4: =IFERROR(IF(AK4<>"OK","",IF(AA4,0,INT(ROUND(MIN(M4,AD4)/(N4*O4),9)))),"INVALID") | AM4: =IFERROR(IF(AK4<>"OK",AK4,IF(AA4,"BREACHED",INT(ROUND((AG4*N4*O4)*100,6))/100)),"INVALID") | AN4: =IFERROR(IF(AND(A4="",B4=""),"",_xlfn.TEXTJOIN("; ",TRUE,IF(C4="partial","PARTIAL PRESET: verify "&IFERROR(INDEX(Presets!$L$2:$L$200,MATCH($B4,Presets!$A$2:$A$200,0))&"",""),""),IF(C4="manual","MANUAL: all params user-entered",""),IF(OR(AND(D4<>"",IFERROR(INDEX(Presets!$C$2:$C$200,MATCH($B4,Presets!$A$2:$A$200,0))&"","")<>""),AND(E4<>"",IFERROR(INDEX(Presets!$D$2:$D$200,MATCH($B4,Presets!$A$2:$A$200,0))&"","")<>""),AND(F4<>"",IFERROR(INDEX(Presets!$E$2:$E$200,MATCH($B4,Presets!$A$2:$A$200,0))&"","")<>""),AND(G4<>"",IFERROR(INDEX(Presets!$G$2:$G$200,MATCH($B4,Presets!$A$2:$A$200,0))&"","")<>""),AND(H4<>"",IFERROR(INDEX(Presets!$H$2:$H$200,MATCH($B4,Presets!$A$2:$A$200,0))&"","")<>""),AND(I4<>"",IFERROR(INDEX(Presets!$I$2:$I$200,MATCH($B4,Presets!$A$2:$A$200,0))&"","")<>""),AND(J4<>"",IFERROR(INDEX(Presets!$J$2:$J$200,MATCH($B4,Presets!$A$2:$A$200,0))&"","")<>"")),"OVERRIDES PRESET",""),IF(AND(A4<>"",V4=""),"MAX CONTRACTS MISSING: enter a number or NONE",""),IF(AND(IFERROR(INDEX(Presets!$N$2:$N$200,MATCH($B4,Presets!$A$2:$A$200,0))&"","")<>"",NOT(ISNUMBER($B$13))),"AS-OF DATE MISSING: enter today in B13 (stale check off)",""),IF(AND(IFERROR(INDEX(Presets!$N$2:$N$200,MATCH($B4,Presets!$A$2:$A$200,0))&"","")<>"",ISNUMBER($B$13)),IF($B$13-DATE(VALUE(LEFT(IFERROR(INDEX(Presets!$N$2:$N$200,MATCH($B4,Presets!$A$2:$A$200,0))&"",""),4)),VALUE(MID(IFERROR(INDEX(Presets!$N$2:$N$200,MATCH($B4,Presets!$A$2:$A$200,0))&"",""),6,2)),VALUE(MID(IFERROR(INDEX(Presets!$N$2:$N$200,MATCH($B4,Presets!$A$2:$A$200,0))&"",""),9,2)))>30,"STALE PRESET: checked "&IFERROR(INDEX(Presets!$N$2:$N$200,MATCH($B4,Presets!$A$2:$A$200,0))&"","")&", over 30 days before As of",""),""),IF(IFERROR(INDEX(Presets!$M$2:$M$200,MATCH($B4,Presets!$A$2:$A$200,0))&"","")<>"","source: "&IFERROR(INDEX(Presets!$M$2:$M$200,MATCH($B4,Presets!$A$2:$A$200,0))&"","")&" checked "&IFERROR(INDEX(Presets!$N$2:$N$200,MATCH($B4,Presets!$A$2:$A$200,0))&"",""),""))),"INVALID")
C5: =IFERROR(INDEX(Presets!$B$2:$B$200,MATCH($B5,Presets!$A$2:$A$200,0))&"","") | P5: =IFERROR(IF(D5<>"",D5,IFERROR(INDEX(Presets!$C$2:$C$200,MATCH($B5,Presets!$A$2:$A$200,0))&"","")),"INVALID") | Q5: =IFERROR(IF(E5<>"",E5,IF(IFERROR(INDEX(Presets!$D$2:$D$200,MATCH($B5,Presets!$A$2:$A$200,0))&"","")<>"",VALUE(IFERROR(INDEX(Presets!$D$2:$D$200,MATCH($B5,Presets!$A$2:$A$200,0))&"","")),"")),"INVALID") | R5: =IFERROR(IF(F5<>"",F5,IF(IFERROR(INDEX(Presets!$E$2:$E$200,MATCH($B5,Presets!$A$2:$A$200,0))&"","")<>"",VALUE(IFERROR(INDEX(Presets!$E$2:$E$200,MATCH($B5,Presets!$A$2:$A$200,0))&"","")),IF(AND(IFERROR(INDEX(Presets!$F$2:$F$200,MATCH($B5,Presets!$A$2:$A$200,0))&"","")<>"",ISNUMBER(Q5)),VALUE(IFERROR(INDEX(Presets!$F$2:$F$200,MATCH($B5,Presets!$A$2:$A$200,0))&"",""))/100*Q5,""))),"INVALID") | S5: =IFERROR(IF(G5<>"",G5,IF(IFERROR(INDEX(Presets!$G$2:$G$200,MATCH($B5,Presets!$A$2:$A$200,0))&"","")="NONE","NONE",IF(IFERROR(INDEX(Presets!$G$2:$G$200,MATCH($B5,Presets!$A$2:$A$200,0))&"","")<>"",VALUE(IFERROR(INDEX(Presets!$G$2:$G$200,MATCH($B5,Presets!$A$2:$A$200,0))&"","")),""))),"INVALID") | T5: =IFERROR(IF(H5<>"",H5,IF(IFERROR(INDEX(Presets!$H$2:$H$200,MATCH($B5,Presets!$A$2:$A$200,0))&"","")="TRUE",TRUE,IF(IFERROR(INDEX(Presets!$H$2:$H$200,MATCH($B5,Presets!$A$2:$A$200,0))&"","")="FALSE",FALSE,""))),"INVALID") | U5: =IFERROR(IF(I5<>"",I5,IF(IFERROR(INDEX(Presets!$I$2:$I$200,MATCH($B5,Presets!$A$2:$A$200,0))&"","")="NONE","NONE",IF(IFERROR(INDEX(Presets!$I$2:$I$200,MATCH($B5,Presets!$A$2:$A$200,0))&"","")<>"",VALUE(IFERROR(INDEX(Presets!$I$2:$I$200,MATCH($B5,Presets!$A$2:$A$200,0))&"","")),""))),"INVALID") | V5: =IFERROR(IF(J5<>"",J5,IF(IFERROR(INDEX(Presets!$J$2:$J$200,MATCH($B5,Presets!$A$2:$A$200,0))&"","")<>"",VALUE(IFERROR(INDEX(Presets!$J$2:$J$200,MATCH($B5,Presets!$A$2:$A$200,0))&"","")),"")),"INVALID") | W5: =IFERROR(IF(AND(A5="",B5=""),"",IF(OR(A5="",B5="",P5="",Q5="",R5="",S5="",T5="",U5="",V5="",K5="",AND(U5<>"NONE",L5="")),"INCOMPLETE",IF(OR(COUNTIFS($A$2:$A$11,A5)>1,AND(P5<>"static",P5<>"eod_trailing",P5<>"intraday_trailing"),NOT(ISNUMBER(Q5)),Q5<=0,ROUND(Q5*100,6)<>INT(ROUND(Q5*100,6)),NOT(ISNUMBER(R5)),R5<=0,ROUND(R5*100,6)<>INT(ROUND(R5*100,6)),AND(S5<>"NONE",NOT(ISNUMBER(S5))),AND(P5="static",S5<>"NONE"),IF(ISNUMBER(S5),ROUND(Q5+S5-(Q5-R5),6)<=0,FALSE),IF(ISNUMBER(S5),OR(S5<-100000000,S5>100000000),FALSE),AND(T5<>TRUE,T5<>FALSE),AND(U5<>"NONE",OR(NOT(ISNUMBER(U5)),U5<=0)),IF(V5="NONE",FALSE,IF(ISNUMBER(V5),OR(V5<0,V5<>INT(V5)),TRUE)),NOT(ISNUMBER(K5)),AND(U5<>"NONE",NOT(ISNUMBER(L5))),Q5>100000000,R5>100000000,K5<=0,K5>100000000,IF(ISNUMBER(U5),U5>100000000,FALSE),IF(ISNUMBER(L5),OR(L5<=0,L5>100000000),FALSE)),"INVALID",IF(COUNTIFS('Daily Log'!$A$2:$A$1001,A5,'Daily Log'!$I$2:$I$1001,"INVALID")>0,"INVALID",IF(OR(COUNTIFS('Daily Log'!$A$2:$A$1001,A5,'Daily Log'!$I$2:$I$1001,"INCOMPLETE")>0,COUNTIFS('Daily Log'!$I$2:$I$1001,"UNKNOWN_ACCOUNT")>0),"INCOMPLETE","OK"))))),"INVALID") | X5: =IFERROR(IF($W5<>"OK",$W5,IF(P5="static",Q5,IF(P5="eod_trailing",MAX(Q5,_xlfn.MAXIFS('Daily Log'!$C$2:$C$1001,'Daily Log'!$A$2:$A$1001,A5)),MAX(Q5,K5,_xlfn.MAXIFS('Daily Log'!$C$2:$C$1001,'Daily Log'!$A$2:$A$1001,A5),_xlfn.MAXIFS('Daily Log'!$D$2:$D$1001,'Daily Log'!$A$2:$A$1001,A5))))),"INVALID") | Y5: =IFERROR(IF($W5<>"OK",$W5,-INT(ROUND(-(AJ5)*100,6))/100),"INVALID") | Z5: =IFERROR(IF($W5<>"OK",$W5,AND(ISNUMBER(S5),P5<>"static",ROUND(X5-R5-(Q5+IF(ISNUMBER(S5),S5,0)),6)>=0)),"INVALID") | AA5: =IFERROR(IF($W5<>"OK",$W5,OR(COUNTIFS('Daily Log'!$A$2:$A$1001,A5,'Daily Log'!$I$2:$I$1001,"BREACHED")>0,IF(T5,ROUND(K5-(AJ5),6)<=0,ROUND(K5-(AJ5),6)<0))),"INVALID") | AB5: =IFERROR(IF($W5<>"OK",$W5,IF(AA5,"BREACHED",INT(ROUND((MAX(0,K5-AJ5))*100,6))/100)),"INVALID") | AC5: =IFERROR(IF($W5<>"OK",$W5,IF(AA5,"BREACHED",IF(U5="NONE","NONE",INT(ROUND((MAX(0,U5-MAX(0,-(K5-L5))))*100,6))/100))),"INVALID") | AD5: =IFERROR(IF($W5<>"OK",$W5,IF(AA5,"BREACHED",IF(AC5="NONE",AB5,MIN(AB5,AC5)))),"INVALID") | AE5: =IFERROR(IF($W5<>"OK",$W5,IF(AA5,"BREACHED",IF(AND(AC5<>"NONE",AC5<AB5),"daily_loss","drawdown"))),"INVALID") | AF5: =IFERROR(IF(AK5<>"OK",AK5,IF(AA5,"BREACHED",INT(ROUND((MIN(M5,AD5))*100,6))/100)),"INVALID") | AG5: =IFERROR(IF(AK5<>"OK",AK5,IF(AA5,"BREACHED",IF(V5="NONE",AL5,MIN(AL5,V5)))),"INVALID") | AH5: =IFERROR(IF(AK5<>"OK",AK5,AND(V5<>"NONE",AL5>V5)),"INVALID") | AI5: =IFERROR(IF(AK5<>"OK",AK5,M5>AD5),"INVALID") | AJ5: =IFERROR(IF($W5<>"OK","",IF(P5="static",Q5-R5,IF(S5="NONE",X5-R5,MIN(X5-R5,Q5+S5)))),"INVALID") | AK5: =IFERROR(IF($W5<>"OK",$W5,IF(OR(M5="",N5="",O5=""),"INCOMPLETE",IF(OR(NOT(ISNUMBER(M5)),M5<0,NOT(ISNUMBER(N5)),N5<1,N5<>INT(N5),NOT(ISNUMBER(O5)),O5<=0,O5>100000,ROUND(O5*1000000,3)<>INT(ROUND(O5*1000000,3)),M5>100000000),"INVALID","OK"))),"INVALID") | AL5: =IFERROR(IF(AK5<>"OK","",IF(AA5,0,INT(ROUND(MIN(M5,AD5)/(N5*O5),9)))),"INVALID") | AM5: =IFERROR(IF(AK5<>"OK",AK5,IF(AA5,"BREACHED",INT(ROUND((AG5*N5*O5)*100,6))/100)),"INVALID") | AN5: =IFERROR(IF(AND(A5="",B5=""),"",_xlfn.TEXTJOIN("; ",TRUE,IF(C5="partial","PARTIAL PRESET: verify "&IFERROR(INDEX(Presets!$L$2:$L$200,MATCH($B5,Presets!$A$2:$A$200,0))&"",""),""),IF(C5="manual","MANUAL: all params user-entered",""),IF(OR(AND(D5<>"",IFERROR(INDEX(Presets!$C$2:$C$200,MATCH($B5,Presets!$A$2:$A$200,0))&"","")<>""),AND(E5<>"",IFERROR(INDEX(Presets!$D$2:$D$200,MATCH($B5,Presets!$A$2:$A$200,0))&"","")<>""),AND(F5<>"",IFERROR(INDEX(Presets!$E$2:$E$200,MATCH($B5,Presets!$A$2:$A$200,0))&"","")<>""),AND(G5<>"",IFERROR(INDEX(Presets!$G$2:$G$200,MATCH($B5,Presets!$A$2:$A$200,0))&"","")<>""),AND(H5<>"",IFERROR(INDEX(Presets!$H$2:$H$200,MATCH($B5,Presets!$A$2:$A$200,0))&"","")<>""),AND(I5<>"",IFERROR(INDEX(Presets!$I$2:$I$200,MATCH($B5,Presets!$A$2:$A$200,0))&"","")<>""),AND(J5<>"",IFERROR(INDEX(Presets!$J$2:$J$200,MATCH($B5,Presets!$A$2:$A$200,0))&"","")<>"")),"OVERRIDES PRESET",""),IF(AND(A5<>"",V5=""),"MAX CONTRACTS MISSING: enter a number or NONE",""),IF(AND(IFERROR(INDEX(Presets!$N$2:$N$200,MATCH($B5,Presets!$A$2:$A$200,0))&"","")<>"",NOT(ISNUMBER($B$13))),"AS-OF DATE MISSING: enter today in B13 (stale check off)",""),IF(AND(IFERROR(INDEX(Presets!$N$2:$N$200,MATCH($B5,Presets!$A$2:$A$200,0))&"","")<>"",ISNUMBER($B$13)),IF($B$13-DATE(VALUE(LEFT(IFERROR(INDEX(Presets!$N$2:$N$200,MATCH($B5,Presets!$A$2:$A$200,0))&"",""),4)),VALUE(MID(IFERROR(INDEX(Presets!$N$2:$N$200,MATCH($B5,Presets!$A$2:$A$200,0))&"",""),6,2)),VALUE(MID(IFERROR(INDEX(Presets!$N$2:$N$200,MATCH($B5,Presets!$A$2:$A$200,0))&"",""),9,2)))>30,"STALE PRESET: checked "&IFERROR(INDEX(Presets!$N$2:$N$200,MATCH($B5,Presets!$A$2:$A$200,0))&"","")&", over 30 days before As of",""),""),IF(IFERROR(INDEX(Presets!$M$2:$M$200,MATCH($B5,Presets!$A$2:$A$200,0))&"","")<>"","source: "&IFERROR(INDEX(Presets!$M$2:$M$200,MATCH($B5,Presets!$A$2:$A$200,0))&"","")&" checked "&IFERROR(INDEX(Presets!$N$2:$N$200,MATCH($B5,Presets!$A$2:$A$200,0))&"",""),""))),"INVALID")
C6: =IFERROR(INDEX(Presets!$B$2:$B$200,MATCH($B6,Presets!$A$2:$A$200,0))&"","") | P6: =IFERROR(IF(D6<>"",D6,IFERROR(INDEX(Presets!$C$2:$C$200,MATCH($B6,Presets!$A$2:$A$200,0))&"","")),"INVALID") | Q6: =IFERROR(IF(E6<>"",E6,IF(IFERROR(INDEX(Presets!$D$2:$D$200,MATCH($B6,Presets!$A$2:$A$200,0))&"","")<>"",VALUE(IFERROR(INDEX(Presets!$D$2:$D$200,MATCH($B6,Presets!$A$2:$A$200,0))&"","")),"")),"INVALID") | R6: =IFERROR(IF(F6<>"",F6,IF(IFERROR(INDEX(Presets!$E$2:$E$200,MATCH($B6,Presets!$A$2:$A$200,0))&"","")<>"",VALUE(IFERROR(INDEX(Presets!$E$2:$E$200,MATCH($B6,Presets!$A$2:$A$200,0))&"","")),IF(AND(IFERROR(INDEX(Presets!$F$2:$F$200,MATCH($B6,Presets!$A$2:$A$200,0))&"","")<>"",ISNUMBER(Q6)),VALUE(IFERROR(INDEX(Presets!$F$2:$F$200,MATCH($B6,Presets!$A$2:$A$200,0))&"",""))/100*Q6,""))),"INVALID") | S6: =IFERROR(IF(G6<>"",G6,IF(IFERROR(INDEX(Presets!$G$2:$G$200,MATCH($B6,Presets!$A$2:$A$200,0))&"","")="NONE","NONE",IF(IFERROR(INDEX(Presets!$G$2:$G$200,MATCH($B6,Presets!$A$2:$A$200,0))&"","")<>"",VALUE(IFERROR(INDEX(Presets!$G$2:$G$200,MATCH($B6,Presets!$A$2:$A$200,0))&"","")),""))),"INVALID") | T6: =IFERROR(IF(H6<>"",H6,IF(IFERROR(INDEX(Presets!$H$2:$H$200,MATCH($B6,Presets!$A$2:$A$200,0))&"","")="TRUE",TRUE,IF(IFERROR(INDEX(Presets!$H$2:$H$200,MATCH($B6,Presets!$A$2:$A$200,0))&"","")="FALSE",FALSE,""))),"INVALID") | U6: =IFERROR(IF(I6<>"",I6,IF(IFERROR(INDEX(Presets!$I$2:$I$200,MATCH($B6,Presets!$A$2:$A$200,0))&"","")="NONE","NONE",IF(IFERROR(INDEX(Presets!$I$2:$I$200,MATCH($B6,Presets!$A$2:$A$200,0))&"","")<>"",VALUE(IFERROR(INDEX(Presets!$I$2:$I$200,MATCH($B6,Presets!$A$2:$A$200,0))&"","")),""))),"INVALID") | V6: =IFERROR(IF(J6<>"",J6,IF(IFERROR(INDEX(Presets!$J$2:$J$200,MATCH($B6,Presets!$A$2:$A$200,0))&"","")<>"",VALUE(IFERROR(INDEX(Presets!$J$2:$J$200,MATCH($B6,Presets!$A$2:$A$200,0))&"","")),"")),"INVALID") | W6: =IFERROR(IF(AND(A6="",B6=""),"",IF(OR(A6="",B6="",P6="",Q6="",R6="",S6="",T6="",U6="",V6="",K6="",AND(U6<>"NONE",L6="")),"INCOMPLETE",IF(OR(COUNTIFS($A$2:$A$11,A6)>1,AND(P6<>"static",P6<>"eod_trailing",P6<>"intraday_trailing"),NOT(ISNUMBER(Q6)),Q6<=0,ROUND(Q6*100,6)<>INT(ROUND(Q6*100,6)),NOT(ISNUMBER(R6)),R6<=0,ROUND(R6*100,6)<>INT(ROUND(R6*100,6)),AND(S6<>"NONE",NOT(ISNUMBER(S6))),AND(P6="static",S6<>"NONE"),IF(ISNUMBER(S6),ROUND(Q6+S6-(Q6-R6),6)<=0,FALSE),IF(ISNUMBER(S6),OR(S6<-100000000,S6>100000000),FALSE),AND(T6<>TRUE,T6<>FALSE),AND(U6<>"NONE",OR(NOT(ISNUMBER(U6)),U6<=0)),IF(V6="NONE",FALSE,IF(ISNUMBER(V6),OR(V6<0,V6<>INT(V6)),TRUE)),NOT(ISNUMBER(K6)),AND(U6<>"NONE",NOT(ISNUMBER(L6))),Q6>100000000,R6>100000000,K6<=0,K6>100000000,IF(ISNUMBER(U6),U6>100000000,FALSE),IF(ISNUMBER(L6),OR(L6<=0,L6>100000000),FALSE)),"INVALID",IF(COUNTIFS('Daily Log'!$A$2:$A$1001,A6,'Daily Log'!$I$2:$I$1001,"INVALID")>0,"INVALID",IF(OR(COUNTIFS('Daily Log'!$A$2:$A$1001,A6,'Daily Log'!$I$2:$I$1001,"INCOMPLETE")>0,COUNTIFS('Daily Log'!$I$2:$I$1001,"UNKNOWN_ACCOUNT")>0),"INCOMPLETE","OK"))))),"INVALID") | X6: =IFERROR(IF($W6<>"OK",$W6,IF(P6="static",Q6,IF(P6="eod_trailing",MAX(Q6,_xlfn.MAXIFS('Daily Log'!$C$2:$C$1001,'Daily Log'!$A$2:$A$1001,A6)),MAX(Q6,K6,_xlfn.MAXIFS('Daily Log'!$C$2:$C$1001,'Daily Log'!$A$2:$A$1001,A6),_xlfn.MAXIFS('Daily Log'!$D$2:$D$1001,'Daily Log'!$A$2:$A$1001,A6))))),"INVALID") | Y6: =IFERROR(IF($W6<>"OK",$W6,-INT(ROUND(-(AJ6)*100,6))/100),"INVALID") | Z6: =IFERROR(IF($W6<>"OK",$W6,AND(ISNUMBER(S6),P6<>"static",ROUND(X6-R6-(Q6+IF(ISNUMBER(S6),S6,0)),6)>=0)),"INVALID") | AA6: =IFERROR(IF($W6<>"OK",$W6,OR(COUNTIFS('Daily Log'!$A$2:$A$1001,A6,'Daily Log'!$I$2:$I$1001,"BREACHED")>0,IF(T6,ROUND(K6-(AJ6),6)<=0,ROUND(K6-(AJ6),6)<0))),"INVALID") | AB6: =IFERROR(IF($W6<>"OK",$W6,IF(AA6,"BREACHED",INT(ROUND((MAX(0,K6-AJ6))*100,6))/100)),"INVALID") | AC6: =IFERROR(IF($W6<>"OK",$W6,IF(AA6,"BREACHED",IF(U6="NONE","NONE",INT(ROUND((MAX(0,U6-MAX(0,-(K6-L6))))*100,6))/100))),"INVALID") | AD6: =IFERROR(IF($W6<>"OK",$W6,IF(AA6,"BREACHED",IF(AC6="NONE",AB6,MIN(AB6,AC6)))),"INVALID") | AE6: =IFERROR(IF($W6<>"OK",$W6,IF(AA6,"BREACHED",IF(AND(AC6<>"NONE",AC6<AB6),"daily_loss","drawdown"))),"INVALID") | AF6: =IFERROR(IF(AK6<>"OK",AK6,IF(AA6,"BREACHED",INT(ROUND((MIN(M6,AD6))*100,6))/100)),"INVALID") | AG6: =IFERROR(IF(AK6<>"OK",AK6,IF(AA6,"BREACHED",IF(V6="NONE",AL6,MIN(AL6,V6)))),"INVALID") | AH6: =IFERROR(IF(AK6<>"OK",AK6,AND(V6<>"NONE",AL6>V6)),"INVALID") | AI6: =IFERROR(IF(AK6<>"OK",AK6,M6>AD6),"INVALID") | AJ6: =IFERROR(IF($W6<>"OK","",IF(P6="static",Q6-R6,IF(S6="NONE",X6-R6,MIN(X6-R6,Q6+S6)))),"INVALID") | AK6: =IFERROR(IF($W6<>"OK",$W6,IF(OR(M6="",N6="",O6=""),"INCOMPLETE",IF(OR(NOT(ISNUMBER(M6)),M6<0,NOT(ISNUMBER(N6)),N6<1,N6<>INT(N6),NOT(ISNUMBER(O6)),O6<=0,O6>100000,ROUND(O6*1000000,3)<>INT(ROUND(O6*1000000,3)),M6>100000000),"INVALID","OK"))),"INVALID") | AL6: =IFERROR(IF(AK6<>"OK","",IF(AA6,0,INT(ROUND(MIN(M6,AD6)/(N6*O6),9)))),"INVALID") | AM6: =IFERROR(IF(AK6<>"OK",AK6,IF(AA6,"BREACHED",INT(ROUND((AG6*N6*O6)*100,6))/100)),"INVALID") | AN6: =IFERROR(IF(AND(A6="",B6=""),"",_xlfn.TEXTJOIN("; ",TRUE,IF(C6="partial","PARTIAL PRESET: verify "&IFERROR(INDEX(Presets!$L$2:$L$200,MATCH($B6,Presets!$A$2:$A$200,0))&"",""),""),IF(C6="manual","MANUAL: all params user-entered",""),IF(OR(AND(D6<>"",IFERROR(INDEX(Presets!$C$2:$C$200,MATCH($B6,Presets!$A$2:$A$200,0))&"","")<>""),AND(E6<>"",IFERROR(INDEX(Presets!$D$2:$D$200,MATCH($B6,Presets!$A$2:$A$200,0))&"","")<>""),AND(F6<>"",IFERROR(INDEX(Presets!$E$2:$E$200,MATCH($B6,Presets!$A$2:$A$200,0))&"","")<>""),AND(G6<>"",IFERROR(INDEX(Presets!$G$2:$G$200,MATCH($B6,Presets!$A$2:$A$200,0))&"","")<>""),AND(H6<>"",IFERROR(INDEX(Presets!$H$2:$H$200,MATCH($B6,Presets!$A$2:$A$200,0))&"","")<>""),AND(I6<>"",IFERROR(INDEX(Presets!$I$2:$I$200,MATCH($B6,Presets!$A$2:$A$200,0))&"","")<>""),AND(J6<>"",IFERROR(INDEX(Presets!$J$2:$J$200,MATCH($B6,Presets!$A$2:$A$200,0))&"","")<>"")),"OVERRIDES PRESET",""),IF(AND(A6<>"",V6=""),"MAX CONTRACTS MISSING: enter a number or NONE",""),IF(AND(IFERROR(INDEX(Presets!$N$2:$N$200,MATCH($B6,Presets!$A$2:$A$200,0))&"","")<>"",NOT(ISNUMBER($B$13))),"AS-OF DATE MISSING: enter today in B13 (stale check off)",""),IF(AND(IFERROR(INDEX(Presets!$N$2:$N$200,MATCH($B6,Presets!$A$2:$A$200,0))&"","")<>"",ISNUMBER($B$13)),IF($B$13-DATE(VALUE(LEFT(IFERROR(INDEX(Presets!$N$2:$N$200,MATCH($B6,Presets!$A$2:$A$200,0))&"",""),4)),VALUE(MID(IFERROR(INDEX(Presets!$N$2:$N$200,MATCH($B6,Presets!$A$2:$A$200,0))&"",""),6,2)),VALUE(MID(IFERROR(INDEX(Presets!$N$2:$N$200,MATCH($B6,Presets!$A$2:$A$200,0))&"",""),9,2)))>30,"STALE PRESET: checked "&IFERROR(INDEX(Presets!$N$2:$N$200,MATCH($B6,Presets!$A$2:$A$200,0))&"","")&", over 30 days before As of",""),""),IF(IFERROR(INDEX(Presets!$M$2:$M$200,MATCH($B6,Presets!$A$2:$A$200,0))&"","")<>"","source: "&IFERROR(INDEX(Presets!$M$2:$M$200,MATCH($B6,Presets!$A$2:$A$200,0))&"","")&" checked "&IFERROR(INDEX(Presets!$N$2:$N$200,MATCH($B6,Presets!$A$2:$A$200,0))&"",""),""))),"INVALID")
C7: =IFERROR(INDEX(Presets!$B$2:$B$200,MATCH($B7,Presets!$A$2:$A$200,0))&"","") | P7: =IFERROR(IF(D7<>"",D7,IFERROR(INDEX(Presets!$C$2:$C$200,MATCH($B7,Presets!$A$2:$A$200,0))&"","")),"INVALID") | Q7: =IFERROR(IF(E7<>"",E7,IF(IFERROR(INDEX(Presets!$D$2:$D$200,MATCH($B7,Presets!$A$2:$A$200,0))&"","")<>"",VALUE(IFERROR(INDEX(Presets!$D$2:$D$200,MATCH($B7,Presets!$A$2:$A$200,0))&"","")),"")),"INVALID") | R7: =IFERROR(IF(F7<>"",F7,IF(IFERROR(INDEX(Presets!$E$2:$E$200,MATCH($B7,Presets!$A$2:$A$200,0))&"","")<>"",VALUE(IFERROR(INDEX(Presets!$E$2:$E$200,MATCH($B7,Presets!$A$2:$A$200,0))&"","")),IF(AND(IFERROR(INDEX(Presets!$F$2:$F$200,MATCH($B7,Presets!$A$2:$A$200,0))&"","")<>"",ISNUMBER(Q7)),VALUE(IFERROR(INDEX(Presets!$F$2:$F$200,MATCH($B7,Presets!$A$2:$A$200,0))&"",""))/100*Q7,""))),"INVALID") | S7: =IFERROR(IF(G7<>"",G7,IF(IFERROR(INDEX(Presets!$G$2:$G$200,MATCH($B7,Presets!$A$2:$A$200,0))&"","")="NONE","NONE",IF(IFERROR(INDEX(Presets!$G$2:$G$200,MATCH($B7,Presets!$A$2:$A$200,0))&"","")<>"",VALUE(IFERROR(INDEX(Presets!$G$2:$G$200,MATCH($B7,Presets!$A$2:$A$200,0))&"","")),""))),"INVALID") | T7: =IFERROR(IF(H7<>"",H7,IF(IFERROR(INDEX(Presets!$H$2:$H$200,MATCH($B7,Presets!$A$2:$A$200,0))&"","")="TRUE",TRUE,IF(IFERROR(INDEX(Presets!$H$2:$H$200,MATCH($B7,Presets!$A$2:$A$200,0))&"","")="FALSE",FALSE,""))),"INVALID") | U7: =IFERROR(IF(I7<>"",I7,IF(IFERROR(INDEX(Presets!$I$2:$I$200,MATCH($B7,Presets!$A$2:$A$200,0))&"","")="NONE","NONE",IF(IFERROR(INDEX(Presets!$I$2:$I$200,MATCH($B7,Presets!$A$2:$A$200,0))&"","")<>"",VALUE(IFERROR(INDEX(Presets!$I$2:$I$200,MATCH($B7,Presets!$A$2:$A$200,0))&"","")),""))),"INVALID") | V7: =IFERROR(IF(J7<>"",J7,IF(IFERROR(INDEX(Presets!$J$2:$J$200,MATCH($B7,Presets!$A$2:$A$200,0))&"","")<>"",VALUE(IFERROR(INDEX(Presets!$J$2:$J$200,MATCH($B7,Presets!$A$2:$A$200,0))&"","")),"")),"INVALID") | W7: =IFERROR(IF(AND(A7="",B7=""),"",IF(OR(A7="",B7="",P7="",Q7="",R7="",S7="",T7="",U7="",V7="",K7="",AND(U7<>"NONE",L7="")),"INCOMPLETE",IF(OR(COUNTIFS($A$2:$A$11,A7)>1,AND(P7<>"static",P7<>"eod_trailing",P7<>"intraday_trailing"),NOT(ISNUMBER(Q7)),Q7<=0,ROUND(Q7*100,6)<>INT(ROUND(Q7*100,6)),NOT(ISNUMBER(R7)),R7<=0,ROUND(R7*100,6)<>INT(ROUND(R7*100,6)),AND(S7<>"NONE",NOT(ISNUMBER(S7))),AND(P7="static",S7<>"NONE"),IF(ISNUMBER(S7),ROUND(Q7+S7-(Q7-R7),6)<=0,FALSE),IF(ISNUMBER(S7),OR(S7<-100000000,S7>100000000),FALSE),AND(T7<>TRUE,T7<>FALSE),AND(U7<>"NONE",OR(NOT(ISNUMBER(U7)),U7<=0)),IF(V7="NONE",FALSE,IF(ISNUMBER(V7),OR(V7<0,V7<>INT(V7)),TRUE)),NOT(ISNUMBER(K7)),AND(U7<>"NONE",NOT(ISNUMBER(L7))),Q7>100000000,R7>100000000,K7<=0,K7>100000000,IF(ISNUMBER(U7),U7>100000000,FALSE),IF(ISNUMBER(L7),OR(L7<=0,L7>100000000),FALSE)),"INVALID",IF(COUNTIFS('Daily Log'!$A$2:$A$1001,A7,'Daily Log'!$I$2:$I$1001,"INVALID")>0,"INVALID",IF(OR(COUNTIFS('Daily Log'!$A$2:$A$1001,A7,'Daily Log'!$I$2:$I$1001,"INCOMPLETE")>0,COUNTIFS('Daily Log'!$I$2:$I$1001,"UNKNOWN_ACCOUNT")>0),"INCOMPLETE","OK"))))),"INVALID") | X7: =IFERROR(IF($W7<>"OK",$W7,IF(P7="static",Q7,IF(P7="eod_trailing",MAX(Q7,_xlfn.MAXIFS('Daily Log'!$C$2:$C$1001,'Daily Log'!$A$2:$A$1001,A7)),MAX(Q7,K7,_xlfn.MAXIFS('Daily Log'!$C$2:$C$1001,'Daily Log'!$A$2:$A$1001,A7),_xlfn.MAXIFS('Daily Log'!$D$2:$D$1001,'Daily Log'!$A$2:$A$1001,A7))))),"INVALID") | Y7: =IFERROR(IF($W7<>"OK",$W7,-INT(ROUND(-(AJ7)*100,6))/100),"INVALID") | Z7: =IFERROR(IF($W7<>"OK",$W7,AND(ISNUMBER(S7),P7<>"static",ROUND(X7-R7-(Q7+IF(ISNUMBER(S7),S7,0)),6)>=0)),"INVALID") | AA7: =IFERROR(IF($W7<>"OK",$W7,OR(COUNTIFS('Daily Log'!$A$2:$A$1001,A7,'Daily Log'!$I$2:$I$1001,"BREACHED")>0,IF(T7,ROUND(K7-(AJ7),6)<=0,ROUND(K7-(AJ7),6)<0))),"INVALID") | AB7: =IFERROR(IF($W7<>"OK",$W7,IF(AA7,"BREACHED",INT(ROUND((MAX(0,K7-AJ7))*100,6))/100)),"INVALID") | AC7: =IFERROR(IF($W7<>"OK",$W7,IF(AA7,"BREACHED",IF(U7="NONE","NONE",INT(ROUND((MAX(0,U7-MAX(0,-(K7-L7))))*100,6))/100))),"INVALID") | AD7: =IFERROR(IF($W7<>"OK",$W7,IF(AA7,"BREACHED",IF(AC7="NONE",AB7,MIN(AB7,AC7)))),"INVALID") | AE7: =IFERROR(IF($W7<>"OK",$W7,IF(AA7,"BREACHED",IF(AND(AC7<>"NONE",AC7<AB7),"daily_loss","drawdown"))),"INVALID") | AF7: =IFERROR(IF(AK7<>"OK",AK7,IF(AA7,"BREACHED",INT(ROUND((MIN(M7,AD7))*100,6))/100)),"INVALID") | AG7: =IFERROR(IF(AK7<>"OK",AK7,IF(AA7,"BREACHED",IF(V7="NONE",AL7,MIN(AL7,V7)))),"INVALID") | AH7: =IFERROR(IF(AK7<>"OK",AK7,AND(V7<>"NONE",AL7>V7)),"INVALID") | AI7: =IFERROR(IF(AK7<>"OK",AK7,M7>AD7),"INVALID") | AJ7: =IFERROR(IF($W7<>"OK","",IF(P7="static",Q7-R7,IF(S7="NONE",X7-R7,MIN(X7-R7,Q7+S7)))),"INVALID") | AK7: =IFERROR(IF($W7<>"OK",$W7,IF(OR(M7="",N7="",O7=""),"INCOMPLETE",IF(OR(NOT(ISNUMBER(M7)),M7<0,NOT(ISNUMBER(N7)),N7<1,N7<>INT(N7),NOT(ISNUMBER(O7)),O7<=0,O7>100000,ROUND(O7*1000000,3)<>INT(ROUND(O7*1000000,3)),M7>100000000),"INVALID","OK"))),"INVALID") | AL7: =IFERROR(IF(AK7<>"OK","",IF(AA7,0,INT(ROUND(MIN(M7,AD7)/(N7*O7),9)))),"INVALID") | AM7: =IFERROR(IF(AK7<>"OK",AK7,IF(AA7,"BREACHED",INT(ROUND((AG7*N7*O7)*100,6))/100)),"INVALID") | AN7: =IFERROR(IF(AND(A7="",B7=""),"",_xlfn.TEXTJOIN("; ",TRUE,IF(C7="partial","PARTIAL PRESET: verify "&IFERROR(INDEX(Presets!$L$2:$L$200,MATCH($B7,Presets!$A$2:$A$200,0))&"",""),""),IF(C7="manual","MANUAL: all params user-entered",""),IF(OR(AND(D7<>"",IFERROR(INDEX(Presets!$C$2:$C$200,MATCH($B7,Presets!$A$2:$A$200,0))&"","")<>""),AND(E7<>"",IFERROR(INDEX(Presets!$D$2:$D$200,MATCH($B7,Presets!$A$2:$A$200,0))&"","")<>""),AND(F7<>"",IFERROR(INDEX(Presets!$E$2:$E$200,MATCH($B7,Presets!$A$2:$A$200,0))&"","")<>""),AND(G7<>"",IFERROR(INDEX(Presets!$G$2:$G$200,MATCH($B7,Presets!$A$2:$A$200,0))&"","")<>""),AND(H7<>"",IFERROR(INDEX(Presets!$H$2:$H$200,MATCH($B7,Presets!$A$2:$A$200,0))&"","")<>""),AND(I7<>"",IFERROR(INDEX(Presets!$I$2:$I$200,MATCH($B7,Presets!$A$2:$A$200,0))&"","")<>""),AND(J7<>"",IFERROR(INDEX(Presets!$J$2:$J$200,MATCH($B7,Presets!$A$2:$A$200,0))&"","")<>"")),"OVERRIDES PRESET",""),IF(AND(A7<>"",V7=""),"MAX CONTRACTS MISSING: enter a number or NONE",""),IF(AND(IFERROR(INDEX(Presets!$N$2:$N$200,MATCH($B7,Presets!$A$2:$A$200,0))&"","")<>"",NOT(ISNUMBER($B$13))),"AS-OF DATE MISSING: enter today in B13 (stale check off)",""),IF(AND(IFERROR(INDEX(Presets!$N$2:$N$200,MATCH($B7,Presets!$A$2:$A$200,0))&"","")<>"",ISNUMBER($B$13)),IF($B$13-DATE(VALUE(LEFT(IFERROR(INDEX(Presets!$N$2:$N$200,MATCH($B7,Presets!$A$2:$A$200,0))&"",""),4)),VALUE(MID(IFERROR(INDEX(Presets!$N$2:$N$200,MATCH($B7,Presets!$A$2:$A$200,0))&"",""),6,2)),VALUE(MID(IFERROR(INDEX(Presets!$N$2:$N$200,MATCH($B7,Presets!$A$2:$A$200,0))&"",""),9,2)))>30,"STALE PRESET: checked "&IFERROR(INDEX(Presets!$N$2:$N$200,MATCH($B7,Presets!$A$2:$A$200,0))&"","")&", over 30 days before As of",""),""),IF(IFERROR(INDEX(Presets!$M$2:$M$200,MATCH($B7,Presets!$A$2:$A$200,0))&"","")<>"","source: "&IFERROR(INDEX(Presets!$M$2:$M$200,MATCH($B7,Presets!$A$2:$A$200,0))&"","")&" checked "&IFERROR(INDEX(Presets!$N$2:$N$200,MATCH($B7,Presets!$A$2:$A$200,0))&"",""),""))),"INVALID")
C8: =IFERROR(INDEX(Presets!$B$2:$B$200,MATCH($B8,Presets!$A$2:$A$200,0))&"","") | P8: =IFERROR(IF(D8<>"",D8,IFERROR(INDEX(Presets!$C$2:$C$200,MATCH($B8,Presets!$A$2:$A$200,0))&"","")),"INVALID") | Q8: =IFERROR(IF(E8<>"",E8,IF(IFERROR(INDEX(Presets!$D$2:$D$200,MATCH($B8,Presets!$A$2:$A$200,0))&"","")<>"",VALUE(IFERROR(INDEX(Presets!$D$2:$D$200,MATCH($B8,Presets!$A$2:$A$200,0))&"","")),"")),"INVALID") | R8: =IFERROR(IF(F8<>"",F8,IF(IFERROR(INDEX(Presets!$E$2:$E$200,MATCH($B8,Presets!$A$2:$A$200,0))&"","")<>"",VALUE(IFERROR(INDEX(Presets!$E$2:$E$200,MATCH($B8,Presets!$A$2:$A$200,0))&"","")),IF(AND(IFERROR(INDEX(Presets!$F$2:$F$200,MATCH($B8,Presets!$A$2:$A$200,0))&"","")<>"",ISNUMBER(Q8)),VALUE(IFERROR(INDEX(Presets!$F$2:$F$200,MATCH($B8,Presets!$A$2:$A$200,0))&"",""))/100*Q8,""))),"INVALID") | S8: =IFERROR(IF(G8<>"",G8,IF(IFERROR(INDEX(Presets!$G$2:$G$200,MATCH($B8,Presets!$A$2:$A$200,0))&"","")="NONE","NONE",IF(IFERROR(INDEX(Presets!$G$2:$G$200,MATCH($B8,Presets!$A$2:$A$200,0))&"","")<>"",VALUE(IFERROR(INDEX(Presets!$G$2:$G$200,MATCH($B8,Presets!$A$2:$A$200,0))&"","")),""))),"INVALID") | T8: =IFERROR(IF(H8<>"",H8,IF(IFERROR(INDEX(Presets!$H$2:$H$200,MATCH($B8,Presets!$A$2:$A$200,0))&"","")="TRUE",TRUE,IF(IFERROR(INDEX(Presets!$H$2:$H$200,MATCH($B8,Presets!$A$2:$A$200,0))&"","")="FALSE",FALSE,""))),"INVALID") | U8: =IFERROR(IF(I8<>"",I8,IF(IFERROR(INDEX(Presets!$I$2:$I$200,MATCH($B8,Presets!$A$2:$A$200,0))&"","")="NONE","NONE",IF(IFERROR(INDEX(Presets!$I$2:$I$200,MATCH($B8,Presets!$A$2:$A$200,0))&"","")<>"",VALUE(IFERROR(INDEX(Presets!$I$2:$I$200,MATCH($B8,Presets!$A$2:$A$200,0))&"","")),""))),"INVALID") | V8: =IFERROR(IF(J8<>"",J8,IF(IFERROR(INDEX(Presets!$J$2:$J$200,MATCH($B8,Presets!$A$2:$A$200,0))&"","")<>"",VALUE(IFERROR(INDEX(Presets!$J$2:$J$200,MATCH($B8,Presets!$A$2:$A$200,0))&"","")),"")),"INVALID") | W8: =IFERROR(IF(AND(A8="",B8=""),"",IF(OR(A8="",B8="",P8="",Q8="",R8="",S8="",T8="",U8="",V8="",K8="",AND(U8<>"NONE",L8="")),"INCOMPLETE",IF(OR(COUNTIFS($A$2:$A$11,A8)>1,AND(P8<>"static",P8<>"eod_trailing",P8<>"intraday_trailing"),NOT(ISNUMBER(Q8)),Q8<=0,ROUND(Q8*100,6)<>INT(ROUND(Q8*100,6)),NOT(ISNUMBER(R8)),R8<=0,ROUND(R8*100,6)<>INT(ROUND(R8*100,6)),AND(S8<>"NONE",NOT(ISNUMBER(S8))),AND(P8="static",S8<>"NONE"),IF(ISNUMBER(S8),ROUND(Q8+S8-(Q8-R8),6)<=0,FALSE),IF(ISNUMBER(S8),OR(S8<-100000000,S8>100000000),FALSE),AND(T8<>TRUE,T8<>FALSE),AND(U8<>"NONE",OR(NOT(ISNUMBER(U8)),U8<=0)),IF(V8="NONE",FALSE,IF(ISNUMBER(V8),OR(V8<0,V8<>INT(V8)),TRUE)),NOT(ISNUMBER(K8)),AND(U8<>"NONE",NOT(ISNUMBER(L8))),Q8>100000000,R8>100000000,K8<=0,K8>100000000,IF(ISNUMBER(U8),U8>100000000,FALSE),IF(ISNUMBER(L8),OR(L8<=0,L8>100000000),FALSE)),"INVALID",IF(COUNTIFS('Daily Log'!$A$2:$A$1001,A8,'Daily Log'!$I$2:$I$1001,"INVALID")>0,"INVALID",IF(OR(COUNTIFS('Daily Log'!$A$2:$A$1001,A8,'Daily Log'!$I$2:$I$1001,"INCOMPLETE")>0,COUNTIFS('Daily Log'!$I$2:$I$1001,"UNKNOWN_ACCOUNT")>0),"INCOMPLETE","OK"))))),"INVALID") | X8: =IFERROR(IF($W8<>"OK",$W8,IF(P8="static",Q8,IF(P8="eod_trailing",MAX(Q8,_xlfn.MAXIFS('Daily Log'!$C$2:$C$1001,'Daily Log'!$A$2:$A$1001,A8)),MAX(Q8,K8,_xlfn.MAXIFS('Daily Log'!$C$2:$C$1001,'Daily Log'!$A$2:$A$1001,A8),_xlfn.MAXIFS('Daily Log'!$D$2:$D$1001,'Daily Log'!$A$2:$A$1001,A8))))),"INVALID") | Y8: =IFERROR(IF($W8<>"OK",$W8,-INT(ROUND(-(AJ8)*100,6))/100),"INVALID") | Z8: =IFERROR(IF($W8<>"OK",$W8,AND(ISNUMBER(S8),P8<>"static",ROUND(X8-R8-(Q8+IF(ISNUMBER(S8),S8,0)),6)>=0)),"INVALID") | AA8: =IFERROR(IF($W8<>"OK",$W8,OR(COUNTIFS('Daily Log'!$A$2:$A$1001,A8,'Daily Log'!$I$2:$I$1001,"BREACHED")>0,IF(T8,ROUND(K8-(AJ8),6)<=0,ROUND(K8-(AJ8),6)<0))),"INVALID") | AB8: =IFERROR(IF($W8<>"OK",$W8,IF(AA8,"BREACHED",INT(ROUND((MAX(0,K8-AJ8))*100,6))/100)),"INVALID") | AC8: =IFERROR(IF($W8<>"OK",$W8,IF(AA8,"BREACHED",IF(U8="NONE","NONE",INT(ROUND((MAX(0,U8-MAX(0,-(K8-L8))))*100,6))/100))),"INVALID") | AD8: =IFERROR(IF($W8<>"OK",$W8,IF(AA8,"BREACHED",IF(AC8="NONE",AB8,MIN(AB8,AC8)))),"INVALID") | AE8: =IFERROR(IF($W8<>"OK",$W8,IF(AA8,"BREACHED",IF(AND(AC8<>"NONE",AC8<AB8),"daily_loss","drawdown"))),"INVALID") | AF8: =IFERROR(IF(AK8<>"OK",AK8,IF(AA8,"BREACHED",INT(ROUND((MIN(M8,AD8))*100,6))/100)),"INVALID") | AG8: =IFERROR(IF(AK8<>"OK",AK8,IF(AA8,"BREACHED",IF(V8="NONE",AL8,MIN(AL8,V8)))),"INVALID") | AH8: =IFERROR(IF(AK8<>"OK",AK8,AND(V8<>"NONE",AL8>V8)),"INVALID") | AI8: =IFERROR(IF(AK8<>"OK",AK8,M8>AD8),"INVALID") | AJ8: =IFERROR(IF($W8<>"OK","",IF(P8="static",Q8-R8,IF(S8="NONE",X8-R8,MIN(X8-R8,Q8+S8)))),"INVALID") | AK8: =IFERROR(IF($W8<>"OK",$W8,IF(OR(M8="",N8="",O8=""),"INCOMPLETE",IF(OR(NOT(ISNUMBER(M8)),M8<0,NOT(ISNUMBER(N8)),N8<1,N8<>INT(N8),NOT(ISNUMBER(O8)),O8<=0,O8>100000,ROUND(O8*1000000,3)<>INT(ROUND(O8*1000000,3)),M8>100000000),"INVALID","OK"))),"INVALID") | AL8: =IFERROR(IF(AK8<>"OK","",IF(AA8,0,INT(ROUND(MIN(M8,AD8)/(N8*O8),9)))),"INVALID") | AM8: =IFERROR(IF(AK8<>"OK",AK8,IF(AA8,"BREACHED",INT(ROUND((AG8*N8*O8)*100,6))/100)),"INVALID") | AN8: =IFERROR(IF(AND(A8="",B8=""),"",_xlfn.TEXTJOIN("; ",TRUE,IF(C8="partial","PARTIAL PRESET: verify "&IFERROR(INDEX(Presets!$L$2:$L$200,MATCH($B8,Presets!$A$2:$A$200,0))&"",""),""),IF(C8="manual","MANUAL: all params user-entered",""),IF(OR(AND(D8<>"",IFERROR(INDEX(Presets!$C$2:$C$200,MATCH($B8,Presets!$A$2:$A$200,0))&"","")<>""),AND(E8<>"",IFERROR(INDEX(Presets!$D$2:$D$200,MATCH($B8,Presets!$A$2:$A$200,0))&"","")<>""),AND(F8<>"",IFERROR(INDEX(Presets!$E$2:$E$200,MATCH($B8,Presets!$A$2:$A$200,0))&"","")<>""),AND(G8<>"",IFERROR(INDEX(Presets!$G$2:$G$200,MATCH($B8,Presets!$A$2:$A$200,0))&"","")<>""),AND(H8<>"",IFERROR(INDEX(Presets!$H$2:$H$200,MATCH($B8,Presets!$A$2:$A$200,0))&"","")<>""),AND(I8<>"",IFERROR(INDEX(Presets!$I$2:$I$200,MATCH($B8,Presets!$A$2:$A$200,0))&"","")<>""),AND(J8<>"",IFERROR(INDEX(Presets!$J$2:$J$200,MATCH($B8,Presets!$A$2:$A$200,0))&"","")<>"")),"OVERRIDES PRESET",""),IF(AND(A8<>"",V8=""),"MAX CONTRACTS MISSING: enter a number or NONE",""),IF(AND(IFERROR(INDEX(Presets!$N$2:$N$200,MATCH($B8,Presets!$A$2:$A$200,0))&"","")<>"",NOT(ISNUMBER($B$13))),"AS-OF DATE MISSING: enter today in B13 (stale check off)",""),IF(AND(IFERROR(INDEX(Presets!$N$2:$N$200,MATCH($B8,Presets!$A$2:$A$200,0))&"","")<>"",ISNUMBER($B$13)),IF($B$13-DATE(VALUE(LEFT(IFERROR(INDEX(Presets!$N$2:$N$200,MATCH($B8,Presets!$A$2:$A$200,0))&"",""),4)),VALUE(MID(IFERROR(INDEX(Presets!$N$2:$N$200,MATCH($B8,Presets!$A$2:$A$200,0))&"",""),6,2)),VALUE(MID(IFERROR(INDEX(Presets!$N$2:$N$200,MATCH($B8,Presets!$A$2:$A$200,0))&"",""),9,2)))>30,"STALE PRESET: checked "&IFERROR(INDEX(Presets!$N$2:$N$200,MATCH($B8,Presets!$A$2:$A$200,0))&"","")&", over 30 days before As of",""),""),IF(IFERROR(INDEX(Presets!$M$2:$M$200,MATCH($B8,Presets!$A$2:$A$200,0))&"","")<>"","source: "&IFERROR(INDEX(Presets!$M$2:$M$200,MATCH($B8,Presets!$A$2:$A$200,0))&"","")&" checked "&IFERROR(INDEX(Presets!$N$2:$N$200,MATCH($B8,Presets!$A$2:$A$200,0))&"",""),""))),"INVALID")
C9: =IFERROR(INDEX(Presets!$B$2:$B$200,MATCH($B9,Presets!$A$2:$A$200,0))&"","") | P9: =IFERROR(IF(D9<>"",D9,IFERROR(INDEX(Presets!$C$2:$C$200,MATCH($B9,Presets!$A$2:$A$200,0))&"","")),"INVALID") | Q9: =IFERROR(IF(E9<>"",E9,IF(IFERROR(INDEX(Presets!$D$2:$D$200,MATCH($B9,Presets!$A$2:$A$200,0))&"","")<>"",VALUE(IFERROR(INDEX(Presets!$D$2:$D$200,MATCH($B9,Presets!$A$2:$A$200,0))&"","")),"")),"INVALID") | R9: =IFERROR(IF(F9<>"",F9,IF(IFERROR(INDEX(Presets!$E$2:$E$200,MATCH($B9,Presets!$A$2:$A$200,0))&"","")<>"",VALUE(IFERROR(INDEX(Presets!$E$2:$E$200,MATCH($B9,Presets!$A$2:$A$200,0))&"","")),IF(AND(IFERROR(INDEX(Presets!$F$2:$F$200,MATCH($B9,Presets!$A$2:$A$200,0))&"","")<>"",ISNUMBER(Q9)),VALUE(IFERROR(INDEX(Presets!$F$2:$F$200,MATCH($B9,Presets!$A$2:$A$200,0))&"",""))/100*Q9,""))),"INVALID") | S9: =IFERROR(IF(G9<>"",G9,IF(IFERROR(INDEX(Presets!$G$2:$G$200,MATCH($B9,Presets!$A$2:$A$200,0))&"","")="NONE","NONE",IF(IFERROR(INDEX(Presets!$G$2:$G$200,MATCH($B9,Presets!$A$2:$A$200,0))&"","")<>"",VALUE(IFERROR(INDEX(Presets!$G$2:$G$200,MATCH($B9,Presets!$A$2:$A$200,0))&"","")),""))),"INVALID") | T9: =IFERROR(IF(H9<>"",H9,IF(IFERROR(INDEX(Presets!$H$2:$H$200,MATCH($B9,Presets!$A$2:$A$200,0))&"","")="TRUE",TRUE,IF(IFERROR(INDEX(Presets!$H$2:$H$200,MATCH($B9,Presets!$A$2:$A$200,0))&"","")="FALSE",FALSE,""))),"INVALID") | U9: =IFERROR(IF(I9<>"",I9,IF(IFERROR(INDEX(Presets!$I$2:$I$200,MATCH($B9,Presets!$A$2:$A$200,0))&"","")="NONE","NONE",IF(IFERROR(INDEX(Presets!$I$2:$I$200,MATCH($B9,Presets!$A$2:$A$200,0))&"","")<>"",VALUE(IFERROR(INDEX(Presets!$I$2:$I$200,MATCH($B9,Presets!$A$2:$A$200,0))&"","")),""))),"INVALID") | V9: =IFERROR(IF(J9<>"",J9,IF(IFERROR(INDEX(Presets!$J$2:$J$200,MATCH($B9,Presets!$A$2:$A$200,0))&"","")<>"",VALUE(IFERROR(INDEX(Presets!$J$2:$J$200,MATCH($B9,Presets!$A$2:$A$200,0))&"","")),"")),"INVALID") | W9: =IFERROR(IF(AND(A9="",B9=""),"",IF(OR(A9="",B9="",P9="",Q9="",R9="",S9="",T9="",U9="",V9="",K9="",AND(U9<>"NONE",L9="")),"INCOMPLETE",IF(OR(COUNTIFS($A$2:$A$11,A9)>1,AND(P9<>"static",P9<>"eod_trailing",P9<>"intraday_trailing"),NOT(ISNUMBER(Q9)),Q9<=0,ROUND(Q9*100,6)<>INT(ROUND(Q9*100,6)),NOT(ISNUMBER(R9)),R9<=0,ROUND(R9*100,6)<>INT(ROUND(R9*100,6)),AND(S9<>"NONE",NOT(ISNUMBER(S9))),AND(P9="static",S9<>"NONE"),IF(ISNUMBER(S9),ROUND(Q9+S9-(Q9-R9),6)<=0,FALSE),IF(ISNUMBER(S9),OR(S9<-100000000,S9>100000000),FALSE),AND(T9<>TRUE,T9<>FALSE),AND(U9<>"NONE",OR(NOT(ISNUMBER(U9)),U9<=0)),IF(V9="NONE",FALSE,IF(ISNUMBER(V9),OR(V9<0,V9<>INT(V9)),TRUE)),NOT(ISNUMBER(K9)),AND(U9<>"NONE",NOT(ISNUMBER(L9))),Q9>100000000,R9>100000000,K9<=0,K9>100000000,IF(ISNUMBER(U9),U9>100000000,FALSE),IF(ISNUMBER(L9),OR(L9<=0,L9>100000000),FALSE)),"INVALID",IF(COUNTIFS('Daily Log'!$A$2:$A$1001,A9,'Daily Log'!$I$2:$I$1001,"INVALID")>0,"INVALID",IF(OR(COUNTIFS('Daily Log'!$A$2:$A$1001,A9,'Daily Log'!$I$2:$I$1001,"INCOMPLETE")>0,COUNTIFS('Daily Log'!$I$2:$I$1001,"UNKNOWN_ACCOUNT")>0),"INCOMPLETE","OK"))))),"INVALID") | X9: =IFERROR(IF($W9<>"OK",$W9,IF(P9="static",Q9,IF(P9="eod_trailing",MAX(Q9,_xlfn.MAXIFS('Daily Log'!$C$2:$C$1001,'Daily Log'!$A$2:$A$1001,A9)),MAX(Q9,K9,_xlfn.MAXIFS('Daily Log'!$C$2:$C$1001,'Daily Log'!$A$2:$A$1001,A9),_xlfn.MAXIFS('Daily Log'!$D$2:$D$1001,'Daily Log'!$A$2:$A$1001,A9))))),"INVALID") | Y9: =IFERROR(IF($W9<>"OK",$W9,-INT(ROUND(-(AJ9)*100,6))/100),"INVALID") | Z9: =IFERROR(IF($W9<>"OK",$W9,AND(ISNUMBER(S9),P9<>"static",ROUND(X9-R9-(Q9+IF(ISNUMBER(S9),S9,0)),6)>=0)),"INVALID") | AA9: =IFERROR(IF($W9<>"OK",$W9,OR(COUNTIFS('Daily Log'!$A$2:$A$1001,A9,'Daily Log'!$I$2:$I$1001,"BREACHED")>0,IF(T9,ROUND(K9-(AJ9),6)<=0,ROUND(K9-(AJ9),6)<0))),"INVALID") | AB9: =IFERROR(IF($W9<>"OK",$W9,IF(AA9,"BREACHED",INT(ROUND((MAX(0,K9-AJ9))*100,6))/100)),"INVALID") | AC9: =IFERROR(IF($W9<>"OK",$W9,IF(AA9,"BREACHED",IF(U9="NONE","NONE",INT(ROUND((MAX(0,U9-MAX(0,-(K9-L9))))*100,6))/100))),"INVALID") | AD9: =IFERROR(IF($W9<>"OK",$W9,IF(AA9,"BREACHED",IF(AC9="NONE",AB9,MIN(AB9,AC9)))),"INVALID") | AE9: =IFERROR(IF($W9<>"OK",$W9,IF(AA9,"BREACHED",IF(AND(AC9<>"NONE",AC9<AB9),"daily_loss","drawdown"))),"INVALID") | AF9: =IFERROR(IF(AK9<>"OK",AK9,IF(AA9,"BREACHED",INT(ROUND((MIN(M9,AD9))*100,6))/100)),"INVALID") | AG9: =IFERROR(IF(AK9<>"OK",AK9,IF(AA9,"BREACHED",IF(V9="NONE",AL9,MIN(AL9,V9)))),"INVALID") | AH9: =IFERROR(IF(AK9<>"OK",AK9,AND(V9<>"NONE",AL9>V9)),"INVALID") | AI9: =IFERROR(IF(AK9<>"OK",AK9,M9>AD9),"INVALID") | AJ9: =IFERROR(IF($W9<>"OK","",IF(P9="static",Q9-R9,IF(S9="NONE",X9-R9,MIN(X9-R9,Q9+S9)))),"INVALID") | AK9: =IFERROR(IF($W9<>"OK",$W9,IF(OR(M9="",N9="",O9=""),"INCOMPLETE",IF(OR(NOT(ISNUMBER(M9)),M9<0,NOT(ISNUMBER(N9)),N9<1,N9<>INT(N9),NOT(ISNUMBER(O9)),O9<=0,O9>100000,ROUND(O9*1000000,3)<>INT(ROUND(O9*1000000,3)),M9>100000000),"INVALID","OK"))),"INVALID") | AL9: =IFERROR(IF(AK9<>"OK","",IF(AA9,0,INT(ROUND(MIN(M9,AD9)/(N9*O9),9)))),"INVALID") | AM9: =IFERROR(IF(AK9<>"OK",AK9,IF(AA9,"BREACHED",INT(ROUND((AG9*N9*O9)*100,6))/100)),"INVALID") | AN9: =IFERROR(IF(AND(A9="",B9=""),"",_xlfn.TEXTJOIN("; ",TRUE,IF(C9="partial","PARTIAL PRESET: verify "&IFERROR(INDEX(Presets!$L$2:$L$200,MATCH($B9,Presets!$A$2:$A$200,0))&"",""),""),IF(C9="manual","MANUAL: all params user-entered",""),IF(OR(AND(D9<>"",IFERROR(INDEX(Presets!$C$2:$C$200,MATCH($B9,Presets!$A$2:$A$200,0))&"","")<>""),AND(E9<>"",IFERROR(INDEX(Presets!$D$2:$D$200,MATCH($B9,Presets!$A$2:$A$200,0))&"","")<>""),AND(F9<>"",IFERROR(INDEX(Presets!$E$2:$E$200,MATCH($B9,Presets!$A$2:$A$200,0))&"","")<>""),AND(G9<>"",IFERROR(INDEX(Presets!$G$2:$G$200,MATCH($B9,Presets!$A$2:$A$200,0))&"","")<>""),AND(H9<>"",IFERROR(INDEX(Presets!$H$2:$H$200,MATCH($B9,Presets!$A$2:$A$200,0))&"","")<>""),AND(I9<>"",IFERROR(INDEX(Presets!$I$2:$I$200,MATCH($B9,Presets!$A$2:$A$200,0))&"","")<>""),AND(J9<>"",IFERROR(INDEX(Presets!$J$2:$J$200,MATCH($B9,Presets!$A$2:$A$200,0))&"","")<>"")),"OVERRIDES PRESET",""),IF(AND(A9<>"",V9=""),"MAX CONTRACTS MISSING: enter a number or NONE",""),IF(AND(IFERROR(INDEX(Presets!$N$2:$N$200,MATCH($B9,Presets!$A$2:$A$200,0))&"","")<>"",NOT(ISNUMBER($B$13))),"AS-OF DATE MISSING: enter today in B13 (stale check off)",""),IF(AND(IFERROR(INDEX(Presets!$N$2:$N$200,MATCH($B9,Presets!$A$2:$A$200,0))&"","")<>"",ISNUMBER($B$13)),IF($B$13-DATE(VALUE(LEFT(IFERROR(INDEX(Presets!$N$2:$N$200,MATCH($B9,Presets!$A$2:$A$200,0))&"",""),4)),VALUE(MID(IFERROR(INDEX(Presets!$N$2:$N$200,MATCH($B9,Presets!$A$2:$A$200,0))&"",""),6,2)),VALUE(MID(IFERROR(INDEX(Presets!$N$2:$N$200,MATCH($B9,Presets!$A$2:$A$200,0))&"",""),9,2)))>30,"STALE PRESET: checked "&IFERROR(INDEX(Presets!$N$2:$N$200,MATCH($B9,Presets!$A$2:$A$200,0))&"","")&", over 30 days before As of",""),""),IF(IFERROR(INDEX(Presets!$M$2:$M$200,MATCH($B9,Presets!$A$2:$A$200,0))&"","")<>"","source: "&IFERROR(INDEX(Presets!$M$2:$M$200,MATCH($B9,Presets!$A$2:$A$200,0))&"","")&" checked "&IFERROR(INDEX(Presets!$N$2:$N$200,MATCH($B9,Presets!$A$2:$A$200,0))&"",""),""))),"INVALID")
C10: =IFERROR(INDEX(Presets!$B$2:$B$200,MATCH($B10,Presets!$A$2:$A$200,0))&"","") | P10: =IFERROR(IF(D10<>"",D10,IFERROR(INDEX(Presets!$C$2:$C$200,MATCH($B10,Presets!$A$2:$A$200,0))&"","")),"INVALID") | Q10: =IFERROR(IF(E10<>"",E10,IF(IFERROR(INDEX(Presets!$D$2:$D$200,MATCH($B10,Presets!$A$2:$A$200,0))&"","")<>"",VALUE(IFERROR(INDEX(Presets!$D$2:$D$200,MATCH($B10,Presets!$A$2:$A$200,0))&"","")),"")),"INVALID") | R10: =IFERROR(IF(F10<>"",F10,IF(IFERROR(INDEX(Presets!$E$2:$E$200,MATCH($B10,Presets!$A$2:$A$200,0))&"","")<>"",VALUE(IFERROR(INDEX(Presets!$E$2:$E$200,MATCH($B10,Presets!$A$2:$A$200,0))&"","")),IF(AND(IFERROR(INDEX(Presets!$F$2:$F$200,MATCH($B10,Presets!$A$2:$A$200,0))&"","")<>"",ISNUMBER(Q10)),VALUE(IFERROR(INDEX(Presets!$F$2:$F$200,MATCH($B10,Presets!$A$2:$A$200,0))&"",""))/100*Q10,""))),"INVALID") | S10: =IFERROR(IF(G10<>"",G10,IF(IFERROR(INDEX(Presets!$G$2:$G$200,MATCH($B10,Presets!$A$2:$A$200,0))&"","")="NONE","NONE",IF(IFERROR(INDEX(Presets!$G$2:$G$200,MATCH($B10,Presets!$A$2:$A$200,0))&"","")<>"",VALUE(IFERROR(INDEX(Presets!$G$2:$G$200,MATCH($B10,Presets!$A$2:$A$200,0))&"","")),""))),"INVALID") | T10: =IFERROR(IF(H10<>"",H10,IF(IFERROR(INDEX(Presets!$H$2:$H$200,MATCH($B10,Presets!$A$2:$A$200,0))&"","")="TRUE",TRUE,IF(IFERROR(INDEX(Presets!$H$2:$H$200,MATCH($B10,Presets!$A$2:$A$200,0))&"","")="FALSE",FALSE,""))),"INVALID") | U10: =IFERROR(IF(I10<>"",I10,IF(IFERROR(INDEX(Presets!$I$2:$I$200,MATCH($B10,Presets!$A$2:$A$200,0))&"","")="NONE","NONE",IF(IFERROR(INDEX(Presets!$I$2:$I$200,MATCH($B10,Presets!$A$2:$A$200,0))&"","")<>"",VALUE(IFERROR(INDEX(Presets!$I$2:$I$200,MATCH($B10,Presets!$A$2:$A$200,0))&"","")),""))),"INVALID") | V10: =IFERROR(IF(J10<>"",J10,IF(IFERROR(INDEX(Presets!$J$2:$J$200,MATCH($B10,Presets!$A$2:$A$200,0))&"","")<>"",VALUE(IFERROR(INDEX(Presets!$J$2:$J$200,MATCH($B10,Presets!$A$2:$A$200,0))&"","")),"")),"INVALID") | W10: =IFERROR(IF(AND(A10="",B10=""),"",IF(OR(A10="",B10="",P10="",Q10="",R10="",S10="",T10="",U10="",V10="",K10="",AND(U10<>"NONE",L10="")),"INCOMPLETE",IF(OR(COUNTIFS($A$2:$A$11,A10)>1,AND(P10<>"static",P10<>"eod_trailing",P10<>"intraday_trailing"),NOT(ISNUMBER(Q10)),Q10<=0,ROUND(Q10*100,6)<>INT(ROUND(Q10*100,6)),NOT(ISNUMBER(R10)),R10<=0,ROUND(R10*100,6)<>INT(ROUND(R10*100,6)),AND(S10<>"NONE",NOT(ISNUMBER(S10))),AND(P10="static",S10<>"NONE"),IF(ISNUMBER(S10),ROUND(Q10+S10-(Q10-R10),6)<=0,FALSE),IF(ISNUMBER(S10),OR(S10<-100000000,S10>100000000),FALSE),AND(T10<>TRUE,T10<>FALSE),AND(U10<>"NONE",OR(NOT(ISNUMBER(U10)),U10<=0)),IF(V10="NONE",FALSE,IF(ISNUMBER(V10),OR(V10<0,V10<>INT(V10)),TRUE)),NOT(ISNUMBER(K10)),AND(U10<>"NONE",NOT(ISNUMBER(L10))),Q10>100000000,R10>100000000,K10<=0,K10>100000000,IF(ISNUMBER(U10),U10>100000000,FALSE),IF(ISNUMBER(L10),OR(L10<=0,L10>100000000),FALSE)),"INVALID",IF(COUNTIFS('Daily Log'!$A$2:$A$1001,A10,'Daily Log'!$I$2:$I$1001,"INVALID")>0,"INVALID",IF(OR(COUNTIFS('Daily Log'!$A$2:$A$1001,A10,'Daily Log'!$I$2:$I$1001,"INCOMPLETE")>0,COUNTIFS('Daily Log'!$I$2:$I$1001,"UNKNOWN_ACCOUNT")>0),"INCOMPLETE","OK"))))),"INVALID") | X10: =IFERROR(IF($W10<>"OK",$W10,IF(P10="static",Q10,IF(P10="eod_trailing",MAX(Q10,_xlfn.MAXIFS('Daily Log'!$C$2:$C$1001,'Daily Log'!$A$2:$A$1001,A10)),MAX(Q10,K10,_xlfn.MAXIFS('Daily Log'!$C$2:$C$1001,'Daily Log'!$A$2:$A$1001,A10),_xlfn.MAXIFS('Daily Log'!$D$2:$D$1001,'Daily Log'!$A$2:$A$1001,A10))))),"INVALID") | Y10: =IFERROR(IF($W10<>"OK",$W10,-INT(ROUND(-(AJ10)*100,6))/100),"INVALID") | Z10: =IFERROR(IF($W10<>"OK",$W10,AND(ISNUMBER(S10),P10<>"static",ROUND(X10-R10-(Q10+IF(ISNUMBER(S10),S10,0)),6)>=0)),"INVALID") | AA10: =IFERROR(IF($W10<>"OK",$W10,OR(COUNTIFS('Daily Log'!$A$2:$A$1001,A10,'Daily Log'!$I$2:$I$1001,"BREACHED")>0,IF(T10,ROUND(K10-(AJ10),6)<=0,ROUND(K10-(AJ10),6)<0))),"INVALID") | AB10: =IFERROR(IF($W10<>"OK",$W10,IF(AA10,"BREACHED",INT(ROUND((MAX(0,K10-AJ10))*100,6))/100)),"INVALID") | AC10: =IFERROR(IF($W10<>"OK",$W10,IF(AA10,"BREACHED",IF(U10="NONE","NONE",INT(ROUND((MAX(0,U10-MAX(0,-(K10-L10))))*100,6))/100))),"INVALID") | AD10: =IFERROR(IF($W10<>"OK",$W10,IF(AA10,"BREACHED",IF(AC10="NONE",AB10,MIN(AB10,AC10)))),"INVALID") | AE10: =IFERROR(IF($W10<>"OK",$W10,IF(AA10,"BREACHED",IF(AND(AC10<>"NONE",AC10<AB10),"daily_loss","drawdown"))),"INVALID") | AF10: =IFERROR(IF(AK10<>"OK",AK10,IF(AA10,"BREACHED",INT(ROUND((MIN(M10,AD10))*100,6))/100)),"INVALID") | AG10: =IFERROR(IF(AK10<>"OK",AK10,IF(AA10,"BREACHED",IF(V10="NONE",AL10,MIN(AL10,V10)))),"INVALID") | AH10: =IFERROR(IF(AK10<>"OK",AK10,AND(V10<>"NONE",AL10>V10)),"INVALID") | AI10: =IFERROR(IF(AK10<>"OK",AK10,M10>AD10),"INVALID") | AJ10: =IFERROR(IF($W10<>"OK","",IF(P10="static",Q10-R10,IF(S10="NONE",X10-R10,MIN(X10-R10,Q10+S10)))),"INVALID") | AK10: =IFERROR(IF($W10<>"OK",$W10,IF(OR(M10="",N10="",O10=""),"INCOMPLETE",IF(OR(NOT(ISNUMBER(M10)),M10<0,NOT(ISNUMBER(N10)),N10<1,N10<>INT(N10),NOT(ISNUMBER(O10)),O10<=0,O10>100000,ROUND(O10*1000000,3)<>INT(ROUND(O10*1000000,3)),M10>100000000),"INVALID","OK"))),"INVALID") | AL10: =IFERROR(IF(AK10<>"OK","",IF(AA10,0,INT(ROUND(MIN(M10,AD10)/(N10*O10),9)))),"INVALID") | AM10: =IFERROR(IF(AK10<>"OK",AK10,IF(AA10,"BREACHED",INT(ROUND((AG10*N10*O10)*100,6))/100)),"INVALID") | AN10: =IFERROR(IF(AND(A10="",B10=""),"",_xlfn.TEXTJOIN("; ",TRUE,IF(C10="partial","PARTIAL PRESET: verify "&IFERROR(INDEX(Presets!$L$2:$L$200,MATCH($B10,Presets!$A$2:$A$200,0))&"",""),""),IF(C10="manual","MANUAL: all params user-entered",""),IF(OR(AND(D10<>"",IFERROR(INDEX(Presets!$C$2:$C$200,MATCH($B10,Presets!$A$2:$A$200,0))&"","")<>""),AND(E10<>"",IFERROR(INDEX(Presets!$D$2:$D$200,MATCH($B10,Presets!$A$2:$A$200,0))&"","")<>""),AND(F10<>"",IFERROR(INDEX(Presets!$E$2:$E$200,MATCH($B10,Presets!$A$2:$A$200,0))&"","")<>""),AND(G10<>"",IFERROR(INDEX(Presets!$G$2:$G$200,MATCH($B10,Presets!$A$2:$A$200,0))&"","")<>""),AND(H10<>"",IFERROR(INDEX(Presets!$H$2:$H$200,MATCH($B10,Presets!$A$2:$A$200,0))&"","")<>""),AND(I10<>"",IFERROR(INDEX(Presets!$I$2:$I$200,MATCH($B10,Presets!$A$2:$A$200,0))&"","")<>""),AND(J10<>"",IFERROR(INDEX(Presets!$J$2:$J$200,MATCH($B10,Presets!$A$2:$A$200,0))&"","")<>"")),"OVERRIDES PRESET",""),IF(AND(A10<>"",V10=""),"MAX CONTRACTS MISSING: enter a number or NONE",""),IF(AND(IFERROR(INDEX(Presets!$N$2:$N$200,MATCH($B10,Presets!$A$2:$A$200,0))&"","")<>"",NOT(ISNUMBER($B$13))),"AS-OF DATE MISSING: enter today in B13 (stale check off)",""),IF(AND(IFERROR(INDEX(Presets!$N$2:$N$200,MATCH($B10,Presets!$A$2:$A$200,0))&"","")<>"",ISNUMBER($B$13)),IF($B$13-DATE(VALUE(LEFT(IFERROR(INDEX(Presets!$N$2:$N$200,MATCH($B10,Presets!$A$2:$A$200,0))&"",""),4)),VALUE(MID(IFERROR(INDEX(Presets!$N$2:$N$200,MATCH($B10,Presets!$A$2:$A$200,0))&"",""),6,2)),VALUE(MID(IFERROR(INDEX(Presets!$N$2:$N$200,MATCH($B10,Presets!$A$2:$A$200,0))&"",""),9,2)))>30,"STALE PRESET: checked "&IFERROR(INDEX(Presets!$N$2:$N$200,MATCH($B10,Presets!$A$2:$A$200,0))&"","")&", over 30 days before As of",""),""),IF(IFERROR(INDEX(Presets!$M$2:$M$200,MATCH($B10,Presets!$A$2:$A$200,0))&"","")<>"","source: "&IFERROR(INDEX(Presets!$M$2:$M$200,MATCH($B10,Presets!$A$2:$A$200,0))&"","")&" checked "&IFERROR(INDEX(Presets!$N$2:$N$200,MATCH($B10,Presets!$A$2:$A$200,0))&"",""),""))),"INVALID")
C11: =IFERROR(INDEX(Presets!$B$2:$B$200,MATCH($B11,Presets!$A$2:$A$200,0))&"","") | P11: =IFERROR(IF(D11<>"",D11,IFERROR(INDEX(Presets!$C$2:$C$200,MATCH($B11,Presets!$A$2:$A$200,0))&"","")),"INVALID") | Q11: =IFERROR(IF(E11<>"",E11,IF(IFERROR(INDEX(Presets!$D$2:$D$200,MATCH($B11,Presets!$A$2:$A$200,0))&"","")<>"",VALUE(IFERROR(INDEX(Presets!$D$2:$D$200,MATCH($B11,Presets!$A$2:$A$200,0))&"","")),"")),"INVALID") | R11: =IFERROR(IF(F11<>"",F11,IF(IFERROR(INDEX(Presets!$E$2:$E$200,MATCH($B11,Presets!$A$2:$A$200,0))&"","")<>"",VALUE(IFERROR(INDEX(Presets!$E$2:$E$200,MATCH($B11,Presets!$A$2:$A$200,0))&"","")),IF(AND(IFERROR(INDEX(Presets!$F$2:$F$200,MATCH($B11,Presets!$A$2:$A$200,0))&"","")<>"",ISNUMBER(Q11)),VALUE(IFERROR(INDEX(Presets!$F$2:$F$200,MATCH($B11,Presets!$A$2:$A$200,0))&"",""))/100*Q11,""))),"INVALID") | S11: =IFERROR(IF(G11<>"",G11,IF(IFERROR(INDEX(Presets!$G$2:$G$200,MATCH($B11,Presets!$A$2:$A$200,0))&"","")="NONE","NONE",IF(IFERROR(INDEX(Presets!$G$2:$G$200,MATCH($B11,Presets!$A$2:$A$200,0))&"","")<>"",VALUE(IFERROR(INDEX(Presets!$G$2:$G$200,MATCH($B11,Presets!$A$2:$A$200,0))&"","")),""))),"INVALID") | T11: =IFERROR(IF(H11<>"",H11,IF(IFERROR(INDEX(Presets!$H$2:$H$200,MATCH($B11,Presets!$A$2:$A$200,0))&"","")="TRUE",TRUE,IF(IFERROR(INDEX(Presets!$H$2:$H$200,MATCH($B11,Presets!$A$2:$A$200,0))&"","")="FALSE",FALSE,""))),"INVALID") | U11: =IFERROR(IF(I11<>"",I11,IF(IFERROR(INDEX(Presets!$I$2:$I$200,MATCH($B11,Presets!$A$2:$A$200,0))&"","")="NONE","NONE",IF(IFERROR(INDEX(Presets!$I$2:$I$200,MATCH($B11,Presets!$A$2:$A$200,0))&"","")<>"",VALUE(IFERROR(INDEX(Presets!$I$2:$I$200,MATCH($B11,Presets!$A$2:$A$200,0))&"","")),""))),"INVALID") | V11: =IFERROR(IF(J11<>"",J11,IF(IFERROR(INDEX(Presets!$J$2:$J$200,MATCH($B11,Presets!$A$2:$A$200,0))&"","")<>"",VALUE(IFERROR(INDEX(Presets!$J$2:$J$200,MATCH($B11,Presets!$A$2:$A$200,0))&"","")),"")),"INVALID") | W11: =IFERROR(IF(AND(A11="",B11=""),"",IF(OR(A11="",B11="",P11="",Q11="",R11="",S11="",T11="",U11="",V11="",K11="",AND(U11<>"NONE",L11="")),"INCOMPLETE",IF(OR(COUNTIFS($A$2:$A$11,A11)>1,AND(P11<>"static",P11<>"eod_trailing",P11<>"intraday_trailing"),NOT(ISNUMBER(Q11)),Q11<=0,ROUND(Q11*100,6)<>INT(ROUND(Q11*100,6)),NOT(ISNUMBER(R11)),R11<=0,ROUND(R11*100,6)<>INT(ROUND(R11*100,6)),AND(S11<>"NONE",NOT(ISNUMBER(S11))),AND(P11="static",S11<>"NONE"),IF(ISNUMBER(S11),ROUND(Q11+S11-(Q11-R11),6)<=0,FALSE),IF(ISNUMBER(S11),OR(S11<-100000000,S11>100000000),FALSE),AND(T11<>TRUE,T11<>FALSE),AND(U11<>"NONE",OR(NOT(ISNUMBER(U11)),U11<=0)),IF(V11="NONE",FALSE,IF(ISNUMBER(V11),OR(V11<0,V11<>INT(V11)),TRUE)),NOT(ISNUMBER(K11)),AND(U11<>"NONE",NOT(ISNUMBER(L11))),Q11>100000000,R11>100000000,K11<=0,K11>100000000,IF(ISNUMBER(U11),U11>100000000,FALSE),IF(ISNUMBER(L11),OR(L11<=0,L11>100000000),FALSE)),"INVALID",IF(COUNTIFS('Daily Log'!$A$2:$A$1001,A11,'Daily Log'!$I$2:$I$1001,"INVALID")>0,"INVALID",IF(OR(COUNTIFS('Daily Log'!$A$2:$A$1001,A11,'Daily Log'!$I$2:$I$1001,"INCOMPLETE")>0,COUNTIFS('Daily Log'!$I$2:$I$1001,"UNKNOWN_ACCOUNT")>0),"INCOMPLETE","OK"))))),"INVALID") | X11: =IFERROR(IF($W11<>"OK",$W11,IF(P11="static",Q11,IF(P11="eod_trailing",MAX(Q11,_xlfn.MAXIFS('Daily Log'!$C$2:$C$1001,'Daily Log'!$A$2:$A$1001,A11)),MAX(Q11,K11,_xlfn.MAXIFS('Daily Log'!$C$2:$C$1001,'Daily Log'!$A$2:$A$1001,A11),_xlfn.MAXIFS('Daily Log'!$D$2:$D$1001,'Daily Log'!$A$2:$A$1001,A11))))),"INVALID") | Y11: =IFERROR(IF($W11<>"OK",$W11,-INT(ROUND(-(AJ11)*100,6))/100),"INVALID") | Z11: =IFERROR(IF($W11<>"OK",$W11,AND(ISNUMBER(S11),P11<>"static",ROUND(X11-R11-(Q11+IF(ISNUMBER(S11),S11,0)),6)>=0)),"INVALID") | AA11: =IFERROR(IF($W11<>"OK",$W11,OR(COUNTIFS('Daily Log'!$A$2:$A$1001,A11,'Daily Log'!$I$2:$I$1001,"BREACHED")>0,IF(T11,ROUND(K11-(AJ11),6)<=0,ROUND(K11-(AJ11),6)<0))),"INVALID") | AB11: =IFERROR(IF($W11<>"OK",$W11,IF(AA11,"BREACHED",INT(ROUND((MAX(0,K11-AJ11))*100,6))/100)),"INVALID") | AC11: =IFERROR(IF($W11<>"OK",$W11,IF(AA11,"BREACHED",IF(U11="NONE","NONE",INT(ROUND((MAX(0,U11-MAX(0,-(K11-L11))))*100,6))/100))),"INVALID") | AD11: =IFERROR(IF($W11<>"OK",$W11,IF(AA11,"BREACHED",IF(AC11="NONE",AB11,MIN(AB11,AC11)))),"INVALID") | AE11: =IFERROR(IF($W11<>"OK",$W11,IF(AA11,"BREACHED",IF(AND(AC11<>"NONE",AC11<AB11),"daily_loss","drawdown"))),"INVALID") | AF11: =IFERROR(IF(AK11<>"OK",AK11,IF(AA11,"BREACHED",INT(ROUND((MIN(M11,AD11))*100,6))/100)),"INVALID") | AG11: =IFERROR(IF(AK11<>"OK",AK11,IF(AA11,"BREACHED",IF(V11="NONE",AL11,MIN(AL11,V11)))),"INVALID") | AH11: =IFERROR(IF(AK11<>"OK",AK11,AND(V11<>"NONE",AL11>V11)),"INVALID") | AI11: =IFERROR(IF(AK11<>"OK",AK11,M11>AD11),"INVALID") | AJ11: =IFERROR(IF($W11<>"OK","",IF(P11="static",Q11-R11,IF(S11="NONE",X11-R11,MIN(X11-R11,Q11+S11)))),"INVALID") | AK11: =IFERROR(IF($W11<>"OK",$W11,IF(OR(M11="",N11="",O11=""),"INCOMPLETE",IF(OR(NOT(ISNUMBER(M11)),M11<0,NOT(ISNUMBER(N11)),N11<1,N11<>INT(N11),NOT(ISNUMBER(O11)),O11<=0,O11>100000,ROUND(O11*1000000,3)<>INT(ROUND(O11*1000000,3)),M11>100000000),"INVALID","OK"))),"INVALID") | AL11: =IFERROR(IF(AK11<>"OK","",IF(AA11,0,INT(ROUND(MIN(M11,AD11)/(N11*O11),9)))),"INVALID") | AM11: =IFERROR(IF(AK11<>"OK",AK11,IF(AA11,"BREACHED",INT(ROUND((AG11*N11*O11)*100,6))/100)),"INVALID") | AN11: =IFERROR(IF(AND(A11="",B11=""),"",_xlfn.TEXTJOIN("; ",TRUE,IF(C11="partial","PARTIAL PRESET: verify "&IFERROR(INDEX(Presets!$L$2:$L$200,MATCH($B11,Presets!$A$2:$A$200,0))&"",""),""),IF(C11="manual","MANUAL: all params user-entered",""),IF(OR(AND(D11<>"",IFERROR(INDEX(Presets!$C$2:$C$200,MATCH($B11,Presets!$A$2:$A$200,0))&"","")<>""),AND(E11<>"",IFERROR(INDEX(Presets!$D$2:$D$200,MATCH($B11,Presets!$A$2:$A$200,0))&"","")<>""),AND(F11<>"",IFERROR(INDEX(Presets!$E$2:$E$200,MATCH($B11,Presets!$A$2:$A$200,0))&"","")<>""),AND(G11<>"",IFERROR(INDEX(Presets!$G$2:$G$200,MATCH($B11,Presets!$A$2:$A$200,0))&"","")<>""),AND(H11<>"",IFERROR(INDEX(Presets!$H$2:$H$200,MATCH($B11,Presets!$A$2:$A$200,0))&"","")<>""),AND(I11<>"",IFERROR(INDEX(Presets!$I$2:$I$200,MATCH($B11,Presets!$A$2:$A$200,0))&"","")<>""),AND(J11<>"",IFERROR(INDEX(Presets!$J$2:$J$200,MATCH($B11,Presets!$A$2:$A$200,0))&"","")<>"")),"OVERRIDES PRESET",""),IF(AND(A11<>"",V11=""),"MAX CONTRACTS MISSING: enter a number or NONE",""),IF(AND(IFERROR(INDEX(Presets!$N$2:$N$200,MATCH($B11,Presets!$A$2:$A$200,0))&"","")<>"",NOT(ISNUMBER($B$13))),"AS-OF DATE MISSING: enter today in B13 (stale check off)",""),IF(AND(IFERROR(INDEX(Presets!$N$2:$N$200,MATCH($B11,Presets!$A$2:$A$200,0))&"","")<>"",ISNUMBER($B$13)),IF($B$13-DATE(VALUE(LEFT(IFERROR(INDEX(Presets!$N$2:$N$200,MATCH($B11,Presets!$A$2:$A$200,0))&"",""),4)),VALUE(MID(IFERROR(INDEX(Presets!$N$2:$N$200,MATCH($B11,Presets!$A$2:$A$200,0))&"",""),6,2)),VALUE(MID(IFERROR(INDEX(Presets!$N$2:$N$200,MATCH($B11,Presets!$A$2:$A$200,0))&"",""),9,2)))>30,"STALE PRESET: checked "&IFERROR(INDEX(Presets!$N$2:$N$200,MATCH($B11,Presets!$A$2:$A$200,0))&"","")&", over 30 days before As of",""),""),IF(IFERROR(INDEX(Presets!$M$2:$M$200,MATCH($B11,Presets!$A$2:$A$200,0))&"","")<>"","source: "&IFERROR(INDEX(Presets!$M$2:$M$200,MATCH($B11,Presets!$A$2:$A$200,0))&"","")&" checked "&IFERROR(INDEX(Presets!$N$2:$N$200,MATCH($B11,Presets!$A$2:$A$200,0))&"",""),""))),"INVALID")
A13: As of | C13: ← today's date (enables the 30-day stale-preset check; no TODAY() used)
A14: Log check | B14: =IF(COUNTIFS('Daily Log'!$I$2:$I$1001,"UNKNOWN_ACCOUNT")>0,COUNTIFS('Daily Log'!$I$2:$I$1001,"UNKNOWN_ACCOUNT")&" Daily Log row(s) with unknown account ID - fix before trading","")
A15: Inputs: shaded cells A–O. Calculated: P–AN (locked). FLOOR / BINDING ROOM / CONTRACTS are the numbers to trade by. Educational only; the firm's dashboard is authoritative.

Sheet Checklist
A1: PRE-SESSION CHECKLIST
A2: Pick the account, tick each line (type x or ✓). Done = 11/11.
A4: # | B4: Done | C4: Account | D4: Check
A5: 1 | D5: Preset matches the plan purchased (firm, plan, size, purchase date — older purchases may have legacy rules).
A6: 2 | D6: Opened source_url; rule text still matches; checked_date within 30 days.
A7: 3 | D7: All needs_user / PARTIAL flags resolved.
A8: 4 | D8: Lock offset confirmed (0 = start, X = start+X, NONE).
A9: 5 | D9: Touch rule confirmed ("hit/touch" = TRUE, "below" = FALSE).
A10: 6 | D10: DLL entered in $ for today's reset (% plans: firm dashboard value).
A11: 7 | D11: Day reference balance = firm's reset reference (incl./excl. unrealized per firm).
A12: 8 | D12: Max contracts entered in the units you trade (micros vs minis).
A13: 9 | D13: Today's Daily Log row entered incl. intraday low.
A14: 10 | D14: Tick value matches Contracts tab for the instrument.
A15: 11 | D15: Firm dashboard floor equals tracker floor; if not, the firm's number wins.
C17: Done | D17: =COUNTIFS(B5:B15,"<>")&" / 11"

Sheet Daily Log
A1: Account ID | B1: Trading date | C1: EOD balance | D1: Intraday high | E1: Intraday low | F1: acct row | G1: Peak (this row) | H1: floor raw | I1: Status | J1: FLOOR
F2: =IFERROR(MATCH($A2,Accounts!$A$2:$A$11,0),"") | G2: =IFERROR(IF(OR($A2="",$F2=""),"",IF(INDEX(Accounts!$P$2:$P$11,$F2)="static",INDEX(Accounts!$Q$2:$Q$11,$F2),IF(INDEX(Accounts!$P$2:$P$11,$F2)="eod_trailing",MAX(INDEX(Accounts!$Q$2:$Q$11,$F2),_xlfn.MAXIFS($C$2:$C$1001,$A$2:$A$1001,$A2,$B$2:$B$1001,"<"&$B2)),MAX(INDEX(Accounts!$Q$2:$Q$11,$F2),_xlfn.MAXIFS($C$2:$C$1001,$A$2:$A$1001,$A2,$B$2:$B$1001,"<"&$B2),_xlfn.MAXIFS($D$2:$D$1001,$A$2:$A$1001,$A2,$B$2:$B$1001,"<="&$B2),$C2)))),"") | H2: =IFERROR(IF(G2="","",IF(INDEX(Accounts!$P$2:$P$11,$F2)="static",INDEX(Accounts!$Q$2:$Q$11,$F2)-INDEX(Accounts!$R$2:$R$11,$F2),IF(INDEX(Accounts!$S$2:$S$11,$F2)="NONE",G2-INDEX(Accounts!$R$2:$R$11,$F2),MIN(G2-INDEX(Accounts!$R$2:$R$11,$F2),INDEX(Accounts!$Q$2:$Q$11,$F2)+INDEX(Accounts!$S$2:$S$11,$F2))))),"") | I2: =IF(AND($A2="",$B2="",$C2="",$D2="",$E2=""),"",IF(OR($A2="",$F2=""),"UNKNOWN_ACCOUNT",IF(OR($B2="",$C2=""),"INCOMPLETE",IFERROR(IF(OR(NOT(ISNUMBER($B2)),NOT(ISNUMBER($C2)),IF(C2="",FALSE,IF(ISNUMBER(C2),OR(C2<=0,C2>100000000,ROUND(C2*100,6)<>INT(ROUND(C2*100,6))),TRUE)),IF(D2="",FALSE,IF(ISNUMBER(D2),OR(D2<=0,D2>100000000,ROUND(D2*100,6)<>INT(ROUND(D2*100,6))),TRUE)),IF(E2="",FALSE,IF(ISNUMBER(E2),OR(E2<=0,E2>100000000,ROUND(E2*100,6)<>INT(ROUND(E2*100,6))),TRUE)),AND($D2<>"",$D2<MAX($C2,$E2)),AND($E2<>"",$E2>MIN($C2,IF($D2="",$C2,$D2))),COUNTIFS($A$2:$A$1001,$A2,$B$2:$B$1001,$B2)>1),"INVALID",IFERROR(IF(IF(INDEX(Accounts!$T$2:$T$11,$F2),ROUND(IF($E2="",$C2,MIN($C2,$E2))-(H2),6)<=0,ROUND(IF($E2="",$C2,MIN($C2,$E2))-(H2),6)<0),"BREACHED","OK"),"INCOMPLETE")),"INVALID")))) | J2: =IF(OR(I2="OK",I2="BREACHED"),-INT(ROUND(-(H2)*100,6))/100,I2)
F3: =IFERROR(MATCH($A3,Accounts!$A$2:$A$11,0),"") | G3: =IFERROR(IF(OR($A3="",$F3=""),"",IF(INDEX(Accounts!$P$2:$P$11,$F3)="static",INDEX(Accounts!$Q$2:$Q$11,$F3),IF(INDEX(Accounts!$P$2:$P$11,$F3)="eod_trailing",MAX(INDEX(Accounts!$Q$2:$Q$11,$F3),_xlfn.MAXIFS($C$2:$C$1001,$A$2:$A$1001,$A3,$B$2:$B$1001,"<"&$B3)),MAX(INDEX(Accounts!$Q$2:$Q$11,$F3),_xlfn.MAXIFS($C$2:$C$1001,$A$2:$A$1001,$A3,$B$2:$B$1001,"<"&$B3),_xlfn.MAXIFS($D$2:$D$1001,$A$2:$A$1001,$A3,$B$2:$B$1001,"<="&$B3),$C3)))),"") | H3: =IFERROR(IF(G3="","",IF(INDEX(Accounts!$P$2:$P$11,$F3)="static",INDEX(Accounts!$Q$2:$Q$11,$F3)-INDEX(Accounts!$R$2:$R$11,$F3),IF(INDEX(Accounts!$S$2:$S$11,$F3)="NONE",G3-INDEX(Accounts!$R$2:$R$11,$F3),MIN(G3-INDEX(Accounts!$R$2:$R$11,$F3),INDEX(Accounts!$Q$2:$Q$11,$F3)+INDEX(Accounts!$S$2:$S$11,$F3))))),"") | I3: =IF(AND($A3="",$B3="",$C3="",$D3="",$E3=""),"",IF(OR($A3="",$F3=""),"UNKNOWN_ACCOUNT",IF(OR($B3="",$C3=""),"INCOMPLETE",IFERROR(IF(OR(NOT(ISNUMBER($B3)),NOT(ISNUMBER($C3)),IF(C3="",FALSE,IF(ISNUMBER(C3),OR(C3<=0,C3>100000000,ROUND(C3*100,6)<>INT(ROUND(C3*100,6))),TRUE)),IF(D3="",FALSE,IF(ISNUMBER(D3),OR(D3<=0,D3>100000000,ROUND(D3*100,6)<>INT(ROUND(D3*100,6))),TRUE)),IF(E3="",FALSE,IF(ISNUMBER(E3),OR(E3<=0,E3>100000000,ROUND(E3*100,6)<>INT(ROUND(E3*100,6))),TRUE)),AND($D3<>"",$D3<MAX($C3,$E3)),AND($E3<>"",$E3>MIN($C3,IF($D3="",$C3,$D3))),COUNTIFS($A$2:$A$1001,$A3,$B$2:$B$1001,$B3)>1),"INVALID",IFERROR(IF(IF(INDEX(Accounts!$T$2:$T$11,$F3),ROUND(IF($E3="",$C3,MIN($C3,$E3))-(H3),6)<=0,ROUND(IF($E3="",$C3,MIN($C3,$E3))-(H3),6)<0),"BREACHED","OK"),"INCOMPLETE")),"INVALID")))) | J3: =IF(OR(I3="OK",I3="BREACHED"),-INT(ROUND(-(H3)*100,6))/100,I3)
F4: =IFERROR(MATCH($A4,Accounts!$A$2:$A$11,0),"") | G4: =IFERROR(IF(OR($A4="",$F4=""),"",IF(INDEX(Accounts!$P$2:$P$11,$F4)="static",INDEX(Accounts!$Q$2:$Q$11,$F4),IF(INDEX(Accounts!$P$2:$P$11,$F4)="eod_trailing",MAX(INDEX(Accounts!$Q$2:$Q$11,$F4),_xlfn.MAXIFS($C$2:$C$1001,$A$2:$A$1001,$A4,$B$2:$B$1001,"<"&$B4)),MAX(INDEX(Accounts!$Q$2:$Q$11,$F4),_xlfn.MAXIFS($C$2:$C$1001,$A$2:$A$1001,$A4,$B$2:$B$1001,"<"&$B4),_xlfn.MAXIFS($D$2:$D$1001,$A$2:$A$1001,$A4,$B$2:$B$1001,"<="&$B4),$C4)))),"") | H4: =IFERROR(IF(G4="","",IF(INDEX(Accounts!$P$2:$P$11,$F4)="static",INDEX(Accounts!$Q$2:$Q$11,$F4)-INDEX(Accounts!$R$2:$R$11,$F4),IF(INDEX(Accounts!$S$2:$S$11,$F4)="NONE",G4-INDEX(Accounts!$R$2:$R$11,$F4),MIN(G4-INDEX(Accounts!$R$2:$R$11,$F4),INDEX(Accounts!$Q$2:$Q$11,$F4)+INDEX(Accounts!$S$2:$S$11,$F4))))),"") | I4: =IF(AND($A4="",$B4="",$C4="",$D4="",$E4=""),"",IF(OR($A4="",$F4=""),"UNKNOWN_ACCOUNT",IF(OR($B4="",$C4=""),"INCOMPLETE",IFERROR(IF(OR(NOT(ISNUMBER($B4)),NOT(ISNUMBER($C4)),IF(C4="",FALSE,IF(ISNUMBER(C4),OR(C4<=0,C4>100000000,ROUND(C4*100,6)<>INT(ROUND(C4*100,6))),TRUE)),IF(D4="",FALSE,IF(ISNUMBER(D4),OR(D4<=0,D4>100000000,ROUND(D4*100,6)<>INT(ROUND(D4*100,6))),TRUE)),IF(E4="",FALSE,IF(ISNUMBER(E4),OR(E4<=0,E4>100000000,ROUND(E4*100,6)<>INT(ROUND(E4*100,6))),TRUE)),AND($D4<>"",$D4<MAX($C4,$E4)),AND($E4<>"",$E4>MIN($C4,IF($D4="",$C4,$D4))),COUNTIFS($A$2:$A$1001,$A4,$B$2:$B$1001,$B4)>1),"INVALID",IFERROR(IF(IF(INDEX(Accounts!$T$2:$T$11,$F4),ROUND(IF($E4="",$C4,MIN($C4,$E4))-(H4),6)<=0,ROUND(IF($E4="",$C4,MIN($C4,$E4))-(H4),6)<0),"BREACHED","OK"),"INCOMPLETE")),"INVALID")))) | J4: =IF(OR(I4="OK",I4="BREACHED"),-INT(ROUND(-(H4)*100,6))/100,I4)
F5: =IFERROR(MATCH($A5,Accounts!$A$2:$A$11,0),"") | G5: =IFERROR(IF(OR($A5="",$F5=""),"",IF(INDEX(Accounts!$P$2:$P$11,$F5)="static",INDEX(Accounts!$Q$2:$Q$11,$F5),IF(INDEX(Accounts!$P$2:$P$11,$F5)="eod_trailing",MAX(INDEX(Accounts!$Q$2:$Q$11,$F5),_xlfn.MAXIFS($C$2:$C$1001,$A$2:$A$1001,$A5,$B$2:$B$1001,"<"&$B5)),MAX(INDEX(Accounts!$Q$2:$Q$11,$F5),_xlfn.MAXIFS($C$2:$C$1001,$A$2:$A$1001,$A5,$B$2:$B$1001,"<"&$B5),_xlfn.MAXIFS($D$2:$D$1001,$A$2:$A$1001,$A5,$B$2:$B$1001,"<="&$B5),$C5)))),"") | H5: =IFERROR(IF(G5="","",IF(INDEX(Accounts!$P$2:$P$11,$F5)="static",INDEX(Accounts!$Q$2:$Q$11,$F5)-INDEX(Accounts!$R$2:$R$11,$F5),IF(INDEX(Accounts!$S$2:$S$11,$F5)="NONE",G5-INDEX(Accounts!$R$2:$R$11,$F5),MIN(G5-INDEX(Accounts!$R$2:$R$11,$F5),INDEX(Accounts!$Q$2:$Q$11,$F5)+INDEX(Accounts!$S$2:$S$11,$F5))))),"") | I5: =IF(AND($A5="",$B5="",$C5="",$D5="",$E5=""),"",IF(OR($A5="",$F5=""),"UNKNOWN_ACCOUNT",IF(OR($B5="",$C5=""),"INCOMPLETE",IFERROR(IF(OR(NOT(ISNUMBER($B5)),NOT(ISNUMBER($C5)),IF(C5="",FALSE,IF(ISNUMBER(C5),OR(C5<=0,C5>100000000,ROUND(C5*100,6)<>INT(ROUND(C5*100,6))),TRUE)),IF(D5="",FALSE,IF(ISNUMBER(D5),OR(D5<=0,D5>100000000,ROUND(D5*100,6)<>INT(ROUND(D5*100,6))),TRUE)),IF(E5="",FALSE,IF(ISNUMBER(E5),OR(E5<=0,E5>100000000,ROUND(E5*100,6)<>INT(ROUND(E5*100,6))),TRUE)),AND($D5<>"",$D5<MAX($C5,$E5)),AND($E5<>"",$E5>MIN($C5,IF($D5="",$C5,$D5))),COUNTIFS($A$2:$A$1001,$A5,$B$2:$B$1001,$B5)>1),"INVALID",IFERROR(IF(IF(INDEX(Accounts!$T$2:$T$11,$F5),ROUND(IF($E5="",$C5,MIN($C5,$E5))-(H5),6)<=0,ROUND(IF($E5="",$C5,MIN($C5,$E5))-(H5),6)<0),"BREACHED","OK"),"INCOMPLETE")),"INVALID")))) | J5: =IF(OR(I5="OK",I5="BREACHED"),-INT(ROUND(-(H5)*100,6))/100,I5)
F6: =IFERROR(MATCH($A6,Accounts!$A$2:$A$11,0),"") | G6: =IFERROR(IF(OR($A6="",$F6=""),"",IF(INDEX(Accounts!$P$2:$P$11,$F6)="static",INDEX(Accounts!$Q$2:$Q$11,$F6),IF(INDEX(Accounts!$P$2:$P$11,$F6)="eod_trailing",MAX(INDEX(Accounts!$Q$2:$Q$11,$F6),_xlfn.MAXIFS($C$2:$C$1001,$A$2:$A$1001,$A6,$B$2:$B$1001,"<"&$B6)),MAX(INDEX(Accounts!$Q$2:$Q$11,$F6),_xlfn.MAXIFS($C$2:$C$1001,$A$2:$A$1001,$A6,$B$2:$B$1001,"<"&$B6),_xlfn.MAXIFS($D$2:$D$1001,$A$2:$A$1001,$A6,$B$2:$B$1001,"<="&$B6),$C6)))),"") | H6: =IFERROR(IF(G6="","",IF(INDEX(Accounts!$P$2:$P$11,$F6)="static",INDEX(Accounts!$Q$2:$Q$11,$F6)-INDEX(Accounts!$R$2:$R$11,$F6),IF(INDEX(Accounts!$S$2:$S$11,$F6)="NONE",G6-INDEX(Accounts!$R$2:$R$11,$F6),MIN(G6-INDEX(Accounts!$R$2:$R$11,$F6),INDEX(Accounts!$Q$2:$Q$11,$F6)+INDEX(Accounts!$S$2:$S$11,$F6))))),"") | I6: =IF(AND($A6="",$B6="",$C6="",$D6="",$E6=""),"",IF(OR($A6="",$F6=""),"UNKNOWN_ACCOUNT",IF(OR($B6="",$C6=""),"INCOMPLETE",IFERROR(IF(OR(NOT(ISNUMBER($B6)),NOT(ISNUMBER($C6)),IF(C6="",FALSE,IF(ISNUMBER(C6),OR(C6<=0,C6>100000000,ROUND(C6*100,6)<>INT(ROUND(C6*100,6))),TRUE)),IF(D6="",FALSE,IF(ISNUMBER(D6),OR(D6<=0,D6>100000000,ROUND(D6*100,6)<>INT(ROUND(D6*100,6))),TRUE)),IF(E6="",FALSE,IF(ISNUMBER(E6),OR(E6<=0,E6>100000000,ROUND(E6*100,6)<>INT(ROUND(E6*100,6))),TRUE)),AND($D6<>"",$D6<MAX($C6,$E6)),AND($E6<>"",$E6>MIN($C6,IF($D6="",$C6,$D6))),COUNTIFS($A$2:$A$1001,$A6,$B$2:$B$1001,$B6)>1),"INVALID",IFERROR(IF(IF(INDEX(Accounts!$T$2:$T$11,$F6),ROUND(IF($E6="",$C6,MIN($C6,$E6))-(H6),6)<=0,ROUND(IF($E6="",$C6,MIN($C6,$E6))-(H6),6)<0),"BREACHED","OK"),"INCOMPLETE")),"INVALID")))) | J6: =IF(OR(I6="OK",I6="BREACHED"),-INT(ROUND(-(H6)*100,6))/100,I6)
F7: =IFERROR(MATCH($A7,Accounts!$A$2:$A$11,0),"") | G7: =IFERROR(IF(OR($A7="",$F7=""),"",IF(INDEX(Accounts!$P$2:$P$11,$F7)="static",INDEX(Accounts!$Q$2:$Q$11,$F7),IF(INDEX(Accounts!$P$2:$P$11,$F7)="eod_trailing",MAX(INDEX(Accounts!$Q$2:$Q$11,$F7),_xlfn.MAXIFS($C$2:$C$1001,$A$2:$A$1001,$A7,$B$2:$B$1001,"<"&$B7)),MAX(INDEX(Accounts!$Q$2:$Q$11,$F7),_xlfn.MAXIFS($C$2:$C$1001,$A$2:$A$1001,$A7,$B$2:$B$1001,"<"&$B7),_xlfn.MAXIFS($D$2:$D$1001,$A$2:$A$1001,$A7,$B$2:$B$1001,"<="&$B7),$C7)))),"") | H7: =IFERROR(IF(G7="","",IF(INDEX(Accounts!$P$2:$P$11,$F7)="static",INDEX(Accounts!$Q$2:$Q$11,$F7)-INDEX(Accounts!$R$2:$R$11,$F7),IF(INDEX(Accounts!$S$2:$S$11,$F7)="NONE",G7-INDEX(Accounts!$R$2:$R$11,$F7),MIN(G7-INDEX(Accounts!$R$2:$R$11,$F7),INDEX(Accounts!$Q$2:$Q$11,$F7)+INDEX(Accounts!$S$2:$S$11,$F7))))),"") | I7: =IF(AND($A7="",$B7="",$C7="",$D7="",$E7=""),"",IF(OR($A7="",$F7=""),"UNKNOWN_ACCOUNT",IF(OR($B7="",$C7=""),"INCOMPLETE",IFERROR(IF(OR(NOT(ISNUMBER($B7)),NOT(ISNUMBER($C7)),IF(C7="",FALSE,IF(ISNUMBER(C7),OR(C7<=0,C7>100000000,ROUND(C7*100,6)<>INT(ROUND(C7*100,6))),TRUE)),IF(D7="",FALSE,IF(ISNUMBER(D7),OR(D7<=0,D7>100000000,ROUND(D7*100,6)<>INT(ROUND(D7*100,6))),TRUE)),IF(E7="",FALSE,IF(ISNUMBER(E7),OR(E7<=0,E7>100000000,ROUND(E7*100,6)<>INT(ROUND(E7*100,6))),TRUE)),AND($D7<>"",$D7<MAX($C7,$E7)),AND($E7<>"",$E7>MIN($C7,IF($D7="",$C7,$D7))),COUNTIFS($A$2:$A$1001,$A7,$B$2:$B$1001,$B7)>1),"INVALID",IFERROR(IF(IF(INDEX(Accounts!$T$2:$T$11,$F7),ROUND(IF($E7="",$C7,MIN($C7,$E7))-(H7),6)<=0,ROUND(IF($E7="",$C7,MIN($C7,$E7))-(H7),6)<0),"BREACHED","OK"),"INCOMPLETE")),"INVALID")))) | J7: =IF(OR(I7="OK",I7="BREACHED"),-INT(ROUND(-(H7)*100,6))/100,I7)
F8: =IFERROR(MATCH($A8,Accounts!$A$2:$A$11,0),"") | G8: =IFERROR(IF(OR($A8="",$F8=""),"",IF(INDEX(Accounts!$P$2:$P$11,$F8)="static",INDEX(Accounts!$Q$2:$Q$11,$F8),IF(INDEX(Accounts!$P$2:$P$11,$F8)="eod_trailing",MAX(INDEX(Accounts!$Q$2:$Q$11,$F8),_xlfn.MAXIFS($C$2:$C$1001,$A$2:$A$1001,$A8,$B$2:$B$1001,"<"&$B8)),MAX(INDEX(Accounts!$Q$2:$Q$11,$F8),_xlfn.MAXIFS($C$2:$C$1001,$A$2:$A$1001,$A8,$B$2:$B$1001,"<"&$B8),_xlfn.MAXIFS($D$2:$D$1001,$A$2:$A$1001,$A8,$B$2:$B$1001,"<="&$B8),$C8)))),"") | H8: =IFERROR(IF(G8="","",IF(INDEX(Accounts!$P$2:$P$11,$F8)="static",INDEX(Accounts!$Q$2:$Q$11,$F8)-INDEX(Accounts!$R$2:$R$11,$F8),IF(INDEX(Accounts!$S$2:$S$11,$F8)="NONE",G8-INDEX(Accounts!$R$2:$R$11,$F8),MIN(G8-INDEX(Accounts!$R$2:$R$11,$F8),INDEX(Accounts!$Q$2:$Q$11,$F8)+INDEX(Accounts!$S$2:$S$11,$F8))))),"") | I8: =IF(AND($A8="",$B8="",$C8="",$D8="",$E8=""),"",IF(OR($A8="",$F8=""),"UNKNOWN_ACCOUNT",IF(OR($B8="",$C8=""),"INCOMPLETE",IFERROR(IF(OR(NOT(ISNUMBER($B8)),NOT(ISNUMBER($C8)),IF(C8="",FALSE,IF(ISNUMBER(C8),OR(C8<=0,C8>100000000,ROUND(C8*100,6)<>INT(ROUND(C8*100,6))),TRUE)),IF(D8="",FALSE,IF(ISNUMBER(D8),OR(D8<=0,D8>100000000,ROUND(D8*100,6)<>INT(ROUND(D8*100,6))),TRUE)),IF(E8="",FALSE,IF(ISNUMBER(E8),OR(E8<=0,E8>100000000,ROUND(E8*100,6)<>INT(ROUND(E8*100,6))),TRUE)),AND($D8<>"",$D8<MAX($C8,$E8)),AND($E8<>"",$E8>MIN($C8,IF($D8="",$C8,$D8))),COUNTIFS($A$2:$A$1001,$A8,$B$2:$B$1001,$B8)>1),"INVALID",IFERROR(IF(IF(INDEX(Accounts!$T$2:$T$11,$F8),ROUND(IF($E8="",$C8,MIN($C8,$E8))-(H8),6)<=0,ROUND(IF($E8="",$C8,MIN($C8,$E8))-(H8),6)<0),"BREACHED","OK"),"INCOMPLETE")),"INVALID")))) | J8: =IF(OR(I8="OK",I8="BREACHED"),-INT(ROUND(-(H8)*100,6))/100,I8)
F9: =IFERROR(MATCH($A9,Accounts!$A$2:$A$11,0),"") | G9: =IFERROR(IF(OR($A9="",$F9=""),"",IF(INDEX(Accounts!$P$2:$P$11,$F9)="static",INDEX(Accounts!$Q$2:$Q$11,$F9),IF(INDEX(Accounts!$P$2:$P$11,$F9)="eod_trailing",MAX(INDEX(Accounts!$Q$2:$Q$11,$F9),_xlfn.MAXIFS($C$2:$C$1001,$A$2:$A$1001,$A9,$B$2:$B$1001,"<"&$B9)),MAX(INDEX(Accounts!$Q$2:$Q$11,$F9),_xlfn.MAXIFS($C$2:$C$1001,$A$2:$A$1001,$A9,$B$2:$B$1001,"<"&$B9),_xlfn.MAXIFS($D$2:$D$1001,$A$2:$A$1001,$A9,$B$2:$B$1001,"<="&$B9),$C9)))),"") | H9: =IFERROR(IF(G9="","",IF(INDEX(Accounts!$P$2:$P$11,$F9)="static",INDEX(Accounts!$Q$2:$Q$11,$F9)-INDEX(Accounts!$R$2:$R$11,$F9),IF(INDEX(Accounts!$S$2:$S$11,$F9)="NONE",G9-INDEX(Accounts!$R$2:$R$11,$F9),MIN(G9-INDEX(Accounts!$R$2:$R$11,$F9),INDEX(Accounts!$Q$2:$Q$11,$F9)+INDEX(Accounts!$S$2:$S$11,$F9))))),"") | I9: =IF(AND($A9="",$B9="",$C9="",$D9="",$E9=""),"",IF(OR($A9="",$F9=""),"UNKNOWN_ACCOUNT",IF(OR($B9="",$C9=""),"INCOMPLETE",IFERROR(IF(OR(NOT(ISNUMBER($B9)),NOT(ISNUMBER($C9)),IF(C9="",FALSE,IF(ISNUMBER(C9),OR(C9<=0,C9>100000000,ROUND(C9*100,6)<>INT(ROUND(C9*100,6))),TRUE)),IF(D9="",FALSE,IF(ISNUMBER(D9),OR(D9<=0,D9>100000000,ROUND(D9*100,6)<>INT(ROUND(D9*100,6))),TRUE)),IF(E9="",FALSE,IF(ISNUMBER(E9),OR(E9<=0,E9>100000000,ROUND(E9*100,6)<>INT(ROUND(E9*100,6))),TRUE)),AND($D9<>"",$D9<MAX($C9,$E9)),AND($E9<>"",$E9>MIN($C9,IF($D9="",$C9,$D9))),COUNTIFS($A$2:$A$1001,$A9,$B$2:$B$1001,$B9)>1),"INVALID",IFERROR(IF(IF(INDEX(Accounts!$T$2:$T$11,$F9),ROUND(IF($E9="",$C9,MIN($C9,$E9))-(H9),6)<=0,ROUND(IF($E9="",$C9,MIN($C9,$E9))-(H9),6)<0),"BREACHED","OK"),"INCOMPLETE")),"INVALID")))) | J9: =IF(OR(I9="OK",I9="BREACHED"),-INT(ROUND(-(H9)*100,6))/100,I9)
F10: =IFERROR(MATCH($A10,Accounts!$A$2:$A$11,0),"") | G10: =IFERROR(IF(OR($A10="",$F10=""),"",IF(INDEX(Accounts!$P$2:$P$11,$F10)="static",INDEX(Accounts!$Q$2:$Q$11,$F10),IF(INDEX(Accounts!$P$2:$P$11,$F10)="eod_trailing",MAX(INDEX(Accounts!$Q$2:$Q$11,$F10),_xlfn.MAXIFS($C$2:$C$1001,$A$2:$A$1001,$A10,$B$2:$B$1001,"<"&$B10)),MAX(INDEX(Accounts!$Q$2:$Q$11,$F10),_xlfn.MAXIFS($C$2:$C$1001,$A$2:$A$1001,$A10,$B$2:$B$1001,"<"&$B10),_xlfn.MAXIFS($D$2:$D$1001,$A$2:$A$1001,$A10,$B$2:$B$1001,"<="&$B10),$C10)))),"") | H10: =IFERROR(IF(G10="","",IF(INDEX(Accounts!$P$2:$P$11,$F10)="static",INDEX(Accounts!$Q$2:$Q$11,$F10)-INDEX(Accounts!$R$2:$R$11,$F10),IF(INDEX(Accounts!$S$2:$S$11,$F10)="NONE",G10-INDEX(Accounts!$R$2:$R$11,$F10),MIN(G10-INDEX(Accounts!$R$2:$R$11,$F10),INDEX(Accounts!$Q$2:$Q$11,$F10)+INDEX(Accounts!$S$2:$S$11,$F10))))),"") | I10: =IF(AND($A10="",$B10="",$C10="",$D10="",$E10=""),"",IF(OR($A10="",$F10=""),"UNKNOWN_ACCOUNT",IF(OR($B10="",$C10=""),"INCOMPLETE",IFERROR(IF(OR(NOT(ISNUMBER($B10)),NOT(ISNUMBER($C10)),IF(C10="",FALSE,IF(ISNUMBER(C10),OR(C10<=0,C10>100000000,ROUND(C10*100,6)<>INT(ROUND(C10*100,6))),TRUE)),IF(D10="",FALSE,IF(ISNUMBER(D10),OR(D10<=0,D10>100000000,ROUND(D10*100,6)<>INT(ROUND(D10*100,6))),TRUE)),IF(E10="",FALSE,IF(ISNUMBER(E10),OR(E10<=0,E10>100000000,ROUND(E10*100,6)<>INT(ROUND(E10*100,6))),TRUE)),AND($D10<>"",$D10<MAX($C10,$E10)),AND($E10<>"",$E10>MIN($C10,IF($D10="",$C10,$D10))),COUNTIFS($A$2:$A$1001,$A10,$B$2:$B$1001,$B10)>1),"INVALID",IFERROR(IF(IF(INDEX(Accounts!$T$2:$T$11,$F10),ROUND(IF($E10="",$C10,MIN($C10,$E10))-(H10),6)<=0,ROUND(IF($E10="",$C10,MIN($C10,$E10))-(H10),6)<0),"BREACHED","OK"),"INCOMPLETE")),"INVALID")))) | J10: =IF(OR(I10="OK",I10="BREACHED"),-INT(ROUND(-(H10)*100,6))/100,I10)
F11: =IFERROR(MATCH($A11,Accounts!$A$2:$A$11,0),"") | G11: =IFERROR(IF(OR($A11="",$F11=""),"",IF(INDEX(Accounts!$P$2:$P$11,$F11)="static",INDEX(Accounts!$Q$2:$Q$11,$F11),IF(INDEX(Accounts!$P$2:$P$11,$F11)="eod_trailing",MAX(INDEX(Accounts!$Q$2:$Q$11,$F11),_xlfn.MAXIFS($C$2:$C$1001,$A$2:$A$1001,$A11,$B$2:$B$1001,"<"&$B11)),MAX(INDEX(Accounts!$Q$2:$Q$11,$F11),_xlfn.MAXIFS($C$2:$C$1001,$A$2:$A$1001,$A11,$B$2:$B$1001,"<"&$B11),_xlfn.MAXIFS($D$2:$D$1001,$A$2:$A$1001,$A11,$B$2:$B$1001,"<="&$B11),$C11)))),"") | H11: =IFERROR(IF(G11="","",IF(INDEX(Accounts!$P$2:$P$11,$F11)="static",INDEX(Accounts!$Q$2:$Q$11,$F11)-INDEX(Accounts!$R$2:$R$11,$F11),IF(INDEX(Accounts!$S$2:$S$11,$F11)="NONE",G11-INDEX(Accounts!$R$2:$R$11,$F11),MIN(G11-INDEX(Accounts!$R$2:$R$11,$F11),INDEX(Accounts!$Q$2:$Q$11,$F11)+INDEX(Accounts!$S$2:$S$11,$F11))))),"") | I11: =IF(AND($A11="",$B11="",$C11="",$D11="",$E11=""),"",IF(OR($A11="",$F11=""),"UNKNOWN_ACCOUNT",IF(OR($B11="",$C11=""),"INCOMPLETE",IFERROR(IF(OR(NOT(ISNUMBER($B11)),NOT(ISNUMBER($C11)),IF(C11="",FALSE,IF(ISNUMBER(C11),OR(C11<=0,C11>100000000,ROUND(C11*100,6)<>INT(ROUND(C11*100,6))),TRUE)),IF(D11="",FALSE,IF(ISNUMBER(D11),OR(D11<=0,D11>100000000,ROUND(D11*100,6)<>INT(ROUND(D11*100,6))),TRUE)),IF(E11="",FALSE,IF(ISNUMBER(E11),OR(E11<=0,E11>100000000,ROUND(E11*100,6)<>INT(ROUND(E11*100,6))),TRUE)),AND($D11<>"",$D11<MAX($C11,$E11)),AND($E11<>"",$E11>MIN($C11,IF($D11="",$C11,$D11))),COUNTIFS($A$2:$A$1001,$A11,$B$2:$B$1001,$B11)>1),"INVALID",IFERROR(IF(IF(INDEX(Accounts!$T$2:$T$11,$F11),ROUND(IF($E11="",$C11,MIN($C11,$E11))-(H11),6)<=0,ROUND(IF($E11="",$C11,MIN($C11,$E11))-(H11),6)<0),"BREACHED","OK"),"INCOMPLETE")),"INVALID")))) | J11: =IF(OR(I11="OK",I11="BREACHED"),-INT(ROUND(-(H11)*100,6))/100,I11)
F12: =IFERROR(MATCH($A12,Accounts!$A$2:$A$11,0),"") | G12: =IFERROR(IF(OR($A12="",$F12=""),"",IF(INDEX(Accounts!$P$2:$P$11,$F12)="static",INDEX(Accounts!$Q$2:$Q$11,$F12),IF(INDEX(Accounts!$P$2:$P$11,$F12)="eod_trailing",MAX(INDEX(Accounts!$Q$2:$Q$11,$F12),_xlfn.MAXIFS($C$2:$C$1001,$A$2:$A$1001,$A12,$B$2:$B$1001,"<"&$B12)),MAX(INDEX(Accounts!$Q$2:$Q$11,$F12),_xlfn.MAXIFS($C$2:$C$1001,$A$2:$A$1001,$A12,$B$2:$B$1001,"<"&$B12),_xlfn.MAXIFS($D$2:$D$1001,$A$2:$A$1001,$A12,$B$2:$B$1001,"<="&$B12),$C12)))),"") | H12: =IFERROR(IF(G12="","",IF(INDEX(Accounts!$P$2:$P$11,$F12)="static",INDEX(Accounts!$Q$2:$Q$11,$F12)-INDEX(Accounts!$R$2:$R$11,$F12),IF(INDEX(Accounts!$S$2:$S$11,$F12)="NONE",G12-INDEX(Accounts!$R$2:$R$11,$F12),MIN(G12-INDEX(Accounts!$R$2:$R$11,$F12),INDEX(Accounts!$Q$2:$Q$11,$F12)+INDEX(Accounts!$S$2:$S$11,$F12))))),"") | I12: =IF(AND($A12="",$B12="",$C12="",$D12="",$E12=""),"",IF(OR($A12="",$F12=""),"UNKNOWN_ACCOUNT",IF(OR($B12="",$C12=""),"INCOMPLETE",IFERROR(IF(OR(NOT(ISNUMBER($B12)),NOT(ISNUMBER($C12)),IF(C12="",FALSE,IF(ISNUMBER(C12),OR(C12<=0,C12>100000000,ROUND(C12*100,6)<>INT(ROUND(C12*100,6))),TRUE)),IF(D12="",FALSE,IF(ISNUMBER(D12),OR(D12<=0,D12>100000000,ROUND(D12*100,6)<>INT(ROUND(D12*100,6))),TRUE)),IF(E12="",FALSE,IF(ISNUMBER(E12),OR(E12<=0,E12>100000000,ROUND(E12*100,6)<>INT(ROUND(E12*100,6))),TRUE)),AND($D12<>"",$D12<MAX($C12,$E12)),AND($E12<>"",$E12>MIN($C12,IF($D12="",$C12,$D12))),COUNTIFS($A$2:$A$1001,$A12,$B$2:$B$1001,$B12)>1),"INVALID",IFERROR(IF(IF(INDEX(Accounts!$T$2:$T$11,$F12),ROUND(IF($E12="",$C12,MIN($C12,$E12))-(H12),6)<=0,ROUND(IF($E12="",$C12,MIN($C12,$E12))-(H12),6)<0),"BREACHED","OK"),"INCOMPLETE")),"INVALID")))) | J12: =IF(OR(I12="OK",I12="BREACHED"),-INT(ROUND(-(H12)*100,6))/100,I12)
F13: =IFERROR(MATCH($A13,Accounts!$A$2:$A$11,0),"") | G13: =IFERROR(IF(OR($A13="",$F13=""),"",IF(INDEX(Accounts!$P$2:$P$11,$F13)="static",INDEX(Accounts!$Q$2:$Q$11,$F13),IF(INDEX(Accounts!$P$2:$P$11,$F13)="eod_trailing",MAX(INDEX(Accounts!$Q$2:$Q$11,$F13),_xlfn.MAXIFS($C$2:$C$1001,$A$2:$A$1001,$A13,$B$2:$B$1001,"<"&$B13)),MAX(INDEX(Accounts!$Q$2:$Q$11,$F13),_xlfn.MAXIFS($C$2:$C$1001,$A$2:$A$1001,$A13,$B$2:$B$1001,"<"&$B13),_xlfn.MAXIFS($D$2:$D$1001,$A$2:$A$1001,$A13,$B$2:$B$1001,"<="&$B13),$C13)))),"") | H13: =IFERROR(IF(G13="","",IF(INDEX(Accounts!$P$2:$P$11,$F13)="static",INDEX(Accounts!$Q$2:$Q$11,$F13)-INDEX(Accounts!$R$2:$R$11,$F13),IF(INDEX(Accounts!$S$2:$S$11,$F13)="NONE",G13-INDEX(Accounts!$R$2:$R$11,$F13),MIN(G13-INDEX(Accounts!$R$2:$R$11,$F13),INDEX(Accounts!$Q$2:$Q$11,$F13)+INDEX(Accounts!$S$2:$S$11,$F13))))),"") | I13: =IF(AND($A13="",$B13="",$C13="",$D13="",$E13=""),"",IF(OR($A13="",$F13=""),"UNKNOWN_ACCOUNT",IF(OR($B13="",$C13=""),"INCOMPLETE",IFERROR(IF(OR(NOT(ISNUMBER($B13)),NOT(ISNUMBER($C13)),IF(C13="",FALSE,IF(ISNUMBER(C13),OR(C13<=0,C13>100000000,ROUND(C13*100,6)<>INT(ROUND(C13*100,6))),TRUE)),IF(D13="",FALSE,IF(ISNUMBER(D13),OR(D13<=0,D13>100000000,ROUND(D13*100,6)<>INT(ROUND(D13*100,6))),TRUE)),IF(E13="",FALSE,IF(ISNUMBER(E13),OR(E13<=0,E13>100000000,ROUND(E13*100,6)<>INT(ROUND(E13*100,6))),TRUE)),AND($D13<>"",$D13<MAX($C13,$E13)),AND($E13<>"",$E13>MIN($C13,IF($D13="",$C13,$D13))),COUNTIFS($A$2:$A$1001,$A13,$B$2:$B$1001,$B13)>1),"INVALID",IFERROR(IF(IF(INDEX(Accounts!$T$2:$T$11,$F13),ROUND(IF($E13="",$C13,MIN($C13,$E13))-(H13),6)<=0,ROUND(IF($E13="",$C13,MIN($C13,$E13))-(H13),6)<0),"BREACHED","OK"),"INCOMPLETE")),"INVALID")))) | J13: =IF(OR(I13="OK",I13="BREACHED"),-INT(ROUND(-(H13)*100,6))/100,I13)
... F1001: =IFERROR(MATCH($A1001,Accounts!$A$2:$A$11,0),"") | G1001: =IFERROR(IF(OR($A1001="",$F1001=""),"",IF(INDEX(Accounts!$P$2:$P$11,$F1001)="static",INDEX(Accounts!$Q$2:$Q$11,$F1001),IF(INDEX(Accounts!$P$2:$P$11,$F1001)="eod_trailing",MAX(INDEX(Accounts!$Q$2:$Q$11,$F1001),_xlfn.MAXIFS($C$2:$C$1001,$A$2:$A$1001,$A1001,$B$2:$B$1001,"<"&$B1001)),MAX(INDEX(Accounts!$Q$2:$Q$11,$F1001),_xlfn.MAXIFS($C$2:$C$1001,$A$2:$A$1001,$A1001,$B$2:$B$1001,"<"&$B1001),_xlfn.MAXIFS($D$2:$D$1001,$A$2:$A$1001,$A1001,$B$2:$B$1001,"<="&$B1001),$C1001)))),"") | H1001: =IFERROR(IF(G1001="","",IF(INDEX(Accounts!$P$2:$P$11,$F1001)="static",INDEX(Accounts!$Q$2:$Q$11,$F1001)-INDEX(Accounts!$R$2:$R$11,$F1001),IF(INDEX(Accounts!$S$2:$S$11,$F1001)="NONE",G1001-INDEX(Accounts!$R$2:$R$11,$F1001),MIN(G1001-INDEX(Accounts!$R$2:$R$11,$F1001),INDEX(Accounts!$Q$2:$Q$11,$F1001)+INDEX(Accounts!$S$2:$S$11,$F1001))))),"") | I1001: =IF(AND($A1001="",$B1001="",$C1001="",$D1001="",$E1001=""),"",IF(OR($A1001="",$F1001=""),"UNKNOWN_ACCOUNT",IF(OR($B1001="",$C1001=""),"INCOMPLETE",IFERROR(IF(OR(NOT(ISNUMBER($B1001)),NOT(ISNUMBER($C1001)),IF(C1001="",FALSE,IF(ISNUMBER(C1001),OR(C1001<=0,C1001>100000000,ROUND(C1001*100,6)<>INT(ROUND(C1001*100,6))),TRUE)),IF(D1001="",FALSE,IF(ISNUMBER(D1001),OR(D1001<=0,D1001>100000000,ROUND(D1001*100,6)<>INT(ROUND(D1001*100,6))),TRUE)),IF(E1001="",FALSE,IF(ISNUMBER(E1001),OR(E1001<=0,E1001>100000000,ROUND(E1001*100,6)<>INT(ROUND(E1001*100,6))),TRUE)),AND($D1001<>"",$D1001<MAX($C1001,$E1001)),AND($E1001<>"",$E1001>MIN($C1001,IF($D1001="",$C1001,$D1001))),COUNTIFS($A$2:$A$1001,$A1001,$B$2:$B$1001,$B1001)>1),"INVALID",IFERROR(IF(IF(INDEX(Accounts!$T$2:$T$11,$F1001),ROUND(IF($E1001="",$C1001,MIN($C1001,$E1001))-(H1001),6)<=0,ROUND(IF($E1001="",$C1001,MIN($C1001,$E1001))-(H1001),6)<0),"BREACHED","OK"),"INCOMPLETE")),"INVALID")))) | J1001: =IF(OR(I1001="OK",I1001="BREACHED"),-INT(ROUND(-(H1001)*100,6))/100,I1001)

Sheet Presets
A1: preset_key | B1: status | C1: dd_type | D1: start_balance | E1: dd_amount | F1: dd_pct | G1: lock_token | H1: breach_on_touch | I1: dll_token | J1: max_contracts | K1: max_micros | L1: needs_user | M1: source_url | N1: checked_date | O1: source_page_date | P1: preset_id
A2: Topstep | Trading Combine | 50000 [P001] | B2: verified | C2: eod_trailing | D2: 50000 | E2: 2000 | G2: 0 | H2: TRUE | J2: 5 | K2: 50 | L2: dll_usd(fixed_usd,optional) | M2: https://help.topstep.com/en/articles/8284204-what-is-the-maximum-loss-limit | N2: 2026-10-14 | P2: P001
A3: Topstep | Trading Combine | 100000 [P002] | B3: verified | C3: eod_trailing | D3: 100000 | E3: 3000 | G3: 0 | H3: TRUE | J3: 10 | K3: 100 | L3: dll_usd(fixed_usd,optional) | M3: https://help.topstep.com/en/articles/8284204-what-is-the-maximum-loss-limit | N3: 2026-10-14 | P3: P002
A4: Topstep | Trading Combine | 150000 [P003] | B4: verified | C4: eod_trailing | D4: 150000 | E4: 4500 | G4: 0 | H4: TRUE | J4: 15 | K4: 150 | L4: dll_usd(fixed_usd,optional) | M4: https://help.topstep.com/en/articles/8284204-what-is-the-maximum-loss-limit | N4: 2026-10-14 | P4: P003
A5: Apex Trader Funding | Intraday Trailing Evaluation | 25000 [P005] | B5: partial | C5: intraday_trailing | D5: 25000 | E5: 1000 | H5: TRUE | I5: NONE | J5: 4 | L5: lock_offset(unstated) | M5: https://apextraderfunding.com/help-center/intraday-trailing-drawdown-accounts/intraday-trailing-drawdown-evaluations/ | N5: 2026-10-14 | O5: 2026-04-28 | P5: P005
A6: Apex Trader Funding | Intraday Trailing Evaluation | 50000 [P006] | B6: partial | C6: intraday_trailing | D6: 50000 | E6: 2000 | H6: TRUE | I6: NONE | J6: 6 | L6: lock_offset(unstated) | M6: https://apextraderfunding.com/help-center/intraday-trailing-drawdown-accounts/intraday-trailing-drawdown-evaluations/ | N6: 2026-10-14 | O6: 2026-04-28 | P6: P006
A7: Apex Trader Funding | Intraday Trailing Evaluation | 100000 [P007] | B7: partial | C7: intraday_trailing | D7: 100000 | E7: 3000 | H7: TRUE | I7: NONE | J7: 8 | L7: lock_offset(unstated) | M7: https://apextraderfunding.com/help-center/intraday-trailing-drawdown-accounts/intraday-trailing-drawdown-evaluations/ | N7: 2026-10-14 | O7: 2026-04-28 | P7: P007
A8: Apex Trader Funding | Intraday Trailing Evaluation | 150000 [P008] | B8: partial | C8: intraday_trailing | D8: 150000 | E8: 4000 | H8: TRUE | I8: NONE | J8: 12 | L8: lock_offset(unstated) | M8: https://apextraderfunding.com/help-center/intraday-trailing-drawdown-accounts/intraday-trailing-drawdown-evaluations/ | N8: 2026-10-14 | O8: 2026-04-28 | P8: P008
A9: Tradeify | Select Evaluation | 25000 [P010] | B9: partial | C9: eod_trailing | D9: 25000 | E9: 1000 | H9: TRUE | I9: NONE | J9: 1 | K9: 10 | L9: lock_offset(unstated) | M9: https://help.tradeify.co/en/articles/12853921-select-evaluation-accounts | N9: 2026-10-14 | O9: 2026-09-10 | P9: P010
A10: Tradeify | Select Evaluation | 50000 [P011] | B10: partial | C10: eod_trailing | D10: 50000 | E10: 2000 | H10: TRUE | I10: NONE | J10: 4 | K10: 40 | L10: lock_offset(unstated) | M10: https://help.tradeify.co/en/articles/12853921-select-evaluation-accounts | N10: 2026-10-14 | O10: 2026-09-10 | P10: P011
A11: Tradeify | Select Evaluation | 100000 [P012] | B11: partial | C11: eod_trailing | D11: 100000 | E11: 3000 | H11: TRUE | I11: NONE | J11: 8 | K11: 80 | L11: lock_offset(unstated) | M11: https://help.tradeify.co/en/articles/12853921-select-evaluation-accounts | N11: 2026-10-14 | O11: 2026-09-10 | P11: P012
A12: Tradeify | Select Evaluation | 150000 [P013] | B12: partial | C12: eod_trailing | D12: 150000 | E12: 4500 | H12: TRUE | I12: NONE | J12: 12 | K12: 120 | L12: lock_offset(unstated) | M12: https://help.tradeify.co/en/articles/12853921-select-evaluation-accounts | N12: 2026-10-14 | O12: 2026-09-10 | P12: P013
A13: MyFundedFutures | Rapid EOD (evaluation) | 50000 [P015] | B13: partial | C13: eod_trailing | D13: 50000 | E13: 2000 | I13: NONE | J13: 3 | K13: 30 | L13: lock_offset(unstated);breach_on_touch | M13: https://help.myfundedfutures.com/en/articles/16158363-rapid-eod-50k-a-comprehensive-look | N13: 2026-10-14 | O13: 2026-08-24 | P13: P015
A14: Lucid Trading | LucidFlex (eval + funded) | 25000 [P018] | B14: partial | C14: eod_trailing | D14: 25000 | E14: 1000 | G14: 100 | H14: TRUE | L14: dll_usd(unstated);max_contracts | M14: https://support.lucidtrading.com/en/articles/12945815-lucidflex-drawdown | N14: 2026-10-14 | O14: 2026-08-26 | P14: P018
A15: Lucid Trading | LucidFlex (eval + funded) | 50000 [P019] | B15: partial | C15: eod_trailing | D15: 50000 | E15: 2000 | G15: 100 | H15: TRUE | L15: dll_usd(unstated);max_contracts | M15: https://support.lucidtrading.com/en/articles/12945815-lucidflex-drawdown | N15: 2026-10-14 | O15: 2026-08-26 | P15: P019
A16: Lucid Trading | LucidFlex (eval + funded) | 100000 [P020] | B16: partial | C16: eod_trailing | D16: 100000 | E16: 3000 | G16: 100 | H16: TRUE | L16: dll_usd(unstated);max_contracts | M16: https://support.lucidtrading.com/en/articles/12945815-lucidflex-drawdown | N16: 2026-10-14 | O16: 2026-08-26 | P16: P020
A17: Lucid Trading | LucidFlex (eval + funded) | 150000 [P021] | B17: partial | C17: eod_trailing | D17: 150000 | E17: 4500 | G17: 100 | H17: TRUE | L17: dll_usd(unstated);max_contracts | M17: https://support.lucidtrading.com/en/articles/12945815-lucidflex-drawdown | N17: 2026-10-14 | O17: 2026-08-26 | P17: P021
A18: Take Profit Trader | Test account (futures) | 25000 [P022] | B18: partial | C18: eod_trailing | D18: 25000 | E18: 1500 | G18: 0 | H18: TRUE | J18: 3 | L18: dll_usd(unstated) | M18: https://takeprofittraderhelp.zendesk.com/hc/en-us/articles/15170265979165-Rule-3-Do-Not-Hit-End-Of-Day-EOD-Maximum-Trailing-Drawdown | N18: 2026-10-14 | O18: 2025-11-13 | P18: P022
A19: Take Profit Trader | Test account (futures) | 50000 [P023] | B19: partial | C19: eod_trailing | D19: 50000 | E19: 2000 | G19: 0 | H19: TRUE | J19: 6 | L19: dll_usd(unstated) | M19: https://takeprofittraderhelp.zendesk.com/hc/en-us/articles/15170265979165-Rule-3-Do-Not-Hit-End-Of-Day-EOD-Maximum-Trailing-Drawdown | N19: 2026-10-14 | O19: 2025-11-13 | P19: P023
A20: Take Profit Trader | Test account (futures) | 75000 [P024] | B20: partial | C20: eod_trailing | D20: 75000 | E20: 2500 | G20: 0 | H20: TRUE | J20: 9 | L20: dll_usd(unstated) | M20: https://takeprofittraderhelp.zendesk.com/hc/en-us/articles/15170265979165-Rule-3-Do-Not-Hit-End-Of-Day-EOD-Maximum-Trailing-Drawdown | N20: 2026-10-14 | O20: 2025-11-13 | P20: P024
A21: Take Profit Trader | Test account (futures) | 100000 [P025] | B21: partial | C21: eod_trailing | D21: 100000 | E21: 3000 | G21: 0 | H21: TRUE | J21: 12 | L21: dll_usd(unstated) | M21: https://takeprofittraderhelp.zendesk.com/hc/en-us/articles/15170265979165-Rule-3-Do-Not-Hit-End-Of-Day-EOD-Maximum-Trailing-Drawdown | N21: 2026-10-14 | O21: 2025-11-13 | P21: P025
A22: Take Profit Trader | Test account (futures) | 150000 [P026] | B22: partial | C22: eod_trailing | D22: 150000 | E22: 4500 | G22: 0 | H22: TRUE | J22: 15 | L22: dll_usd(unstated) | M22: https://takeprofittraderhelp.zendesk.com/hc/en-us/articles/15170265979165-Rule-3-Do-Not-Hit-End-Of-Day-EOD-Maximum-Trailing-Drawdown | N22: 2026-10-14 | O22: 2025-11-13 | P22: P026
A23: Vest (Vest Capital) | Instant | 500 [P027] | B23: verified | C23: static | D23: 500 | E23: 10 | G23: NONE | H23: FALSE | I23: NONE | L23: max_contracts | M23: https://docs.vestmarkets.com/vest-capital/loss-limits | N23: 2026-10-14 | P23: P027
A24: Vest (Vest Capital) | Instant | 5000 [P028] | B24: verified | C24: static | D24: 5000 | E24: 200 | G24: NONE | H24: FALSE | I24: NONE | L24: max_contracts | M24: https://docs.vestmarkets.com/vest-capital/loss-limits | N24: 2026-10-14 | P24: P028
A25: Vest (Vest Capital) | Instant | 10000 [P029] | B25: verified | C25: static | D25: 10000 | E25: 400 | G25: NONE | H25: FALSE | I25: NONE | L25: max_contracts | M25: https://docs.vestmarkets.com/vest-capital/loss-limits | N25: 2026-10-14 | P25: P029
A26: Vest (Vest Capital) | Instant | 25000 [P030] | B26: verified | C26: static | D26: 25000 | E26: 1000 | G26: NONE | H26: FALSE | I26: NONE | L26: max_contracts | M26: https://docs.vestmarkets.com/vest-capital/loss-limits | N26: 2026-10-14 | P26: P030
A27: Vest (Vest Capital) | Evaluation | 5000 [P031] | B27: verified | C27: static | D27: 5000 | E27: 300 | F27: 6 | G27: NONE | H27: FALSE | L27: dll_usd(pct_choice,optional);max_contracts | M27: https://docs.vestmarkets.com/vest-capital/loss-limits | N27: 2026-10-14 | P27: P031
A28: Vest (Vest Capital) | Evaluation | 10000 [P032] | B28: verified | C28: static | D28: 10000 | E28: 600 | F28: 6 | G28: NONE | H28: FALSE | L28: dll_usd(pct_choice,optional);max_contracts | M28: https://docs.vestmarkets.com/vest-capital/loss-limits | N28: 2026-10-14 | P28: P032
A29: Vest (Vest Capital) | Evaluation | 25000 [P033] | B29: verified | C29: static | D29: 25000 | E29: 1500 | F29: 6 | G29: NONE | H29: FALSE | L29: dll_usd(pct_choice,optional);max_contracts | M29: https://docs.vestmarkets.com/vest-capital/loss-limits | N29: 2026-10-14 | P29: P033
A30: Breakout | Evaluation 1-Step Classic | 5000 [P034] | B30: verified | C30: static | D30: 5000 | E30: 300 | G30: NONE | H30: TRUE | L30: dll_usd(pct);max_contracts | M30: https://www.breakoutprop.com/program-rules/ | N30: 2026-10-14 | O30: 2026-07-29 | P30: P034
A31: Breakout | Evaluation 1-Step Classic | 10000 [P035] | B31: verified | C31: static | D31: 10000 | E31: 600 | G31: NONE | H31: TRUE | L31: dll_usd(pct);max_contracts | M31: https://www.breakoutprop.com/program-rules/ | N31: 2026-10-14 | O31: 2026-07-29 | P31: P035
A32: Breakout | Evaluation 1-Step Classic | 25000 [P036] | B32: verified | C32: static | D32: 25000 | E32: 1500 | G32: NONE | H32: TRUE | L32: dll_usd(pct);max_contracts | M32: https://www.breakoutprop.com/program-rules/ | N32: 2026-10-14 | O32: 2026-07-29 | P32: P036
A33: Breakout | Evaluation 1-Step Classic | 50000 [P037] | B33: verified | C33: static | D33: 50000 | E33: 3000 | G33: NONE | H33: TRUE | L33: dll_usd(pct);max_contracts | M33: https://www.breakoutprop.com/program-rules/ | N33: 2026-10-14 | O33: 2026-07-29 | P33: P037
A34: Breakout | Evaluation 1-Step Classic | 100000 [P038] | B34: verified | C34: static | D34: 100000 | E34: 6000 | G34: NONE | H34: TRUE | L34: dll_usd(pct);max_contracts | M34: https://www.breakoutprop.com/program-rules/ | N34: 2026-10-14 | O34: 2026-07-29 | P34: P038
A35: Breakout | Evaluation 1-Step Pro | 5000 [P039] | B35: verified | C35: static | D35: 5000 | E35: 250 | G35: NONE | H35: TRUE | L35: dll_usd(pct);max_contracts | M35: https://www.breakoutprop.com/program-rules/ | N35: 2026-10-14 | O35: 2026-07-29 | P35: P039
A36: Breakout | Evaluation 1-Step Pro | 10000 [P040] | B36: verified | C36: static | D36: 10000 | E36: 500 | G36: NONE | H36: TRUE | L36: dll_usd(pct);max_contracts | M36: https://www.breakoutprop.com/program-rules/ | N36: 2026-10-14 | O36: 2026-07-29 | P36: P040
A37: Breakout | Evaluation 1-Step Pro | 25000 [P041] | B37: verified | C37: static | D37: 25000 | E37: 1250 | G37: NONE | H37: TRUE | L37: dll_usd(pct);max_contracts | M37: https://www.breakoutprop.com/program-rules/ | N37: 2026-10-14 | O37: 2026-07-29 | P37: P041
A38: Breakout | Evaluation 1-Step Pro | 50000 [P042] | B38: verified | C38: static | D38: 50000 | E38: 2500 | G38: NONE | H38: TRUE | L38: dll_usd(pct);max_contracts | M38: https://www.breakoutprop.com/program-rules/ | N38: 2026-10-14 | O38: 2026-07-29 | P38: P042
A39: Breakout | Evaluation 1-Step Pro | 100000 [P043] | B39: verified | C39: static | D39: 100000 | E39: 5000 | G39: NONE | H39: TRUE | L39: dll_usd(pct);max_contracts | M39: https://www.breakoutprop.com/program-rules/ | N39: 2026-10-14 | O39: 2026-07-29 | P39: P043
A40: Breakout | Evaluation 1-Step Pro | 200000 [P044] | B40: verified | C40: static | D40: 200000 | E40: 10000 | G40: NONE | H40: TRUE | L40: dll_usd(pct);max_contracts | M40: https://www.breakoutprop.com/program-rules/ | N40: 2026-10-14 | O40: 2026-07-29 | P40: P044
A41: Breakout | Evaluation 1-Step Turbo | 5000 [P045] | B41: verified | C41: static | D41: 5000 | E41: 150 | G41: NONE | H41: TRUE | L41: dll_usd(pct);max_contracts | M41: https://www.breakoutprop.com/program-rules/ | N41: 2026-10-14 | O41: 2026-07-29 | P41: P045
... A46: Breakout | Evaluation 1-Step Turbo | 200000 [P050] | B46: verified | C46: static | D46: 200000 | E46: 6000 | G46: NONE | H46: TRUE | L46: dll_usd(pct);max_contracts | M46: https://www.breakoutprop.com/program-rules/ | N46: 2026-10-14 | O46: 2026-07-29 | P46: P050
A47: MyFundedPerps | Evaluation 1-Step Select | size? [P051] | B47: verified | C47: static | F47: 3 | G47: NONE | H47: TRUE | L47: dll_usd(pct_of_start);max_contracts;start_balance;touch_after_lock_not_modeled | M47: https://docs.myfundedperpetuals.com/guides/challenges-and-rules | N47: 2026-10-14 | P47: P051
A48: MyFundedPerps | Evaluation 1-Step Prime | size? [P052] | B48: verified | C48: static | F48: 5 | G48: NONE | H48: TRUE | L48: dll_usd(pct_of_start);max_contracts;start_balance;touch_after_lock_not_modeled | M48: https://docs.myfundedperpetuals.com/guides/challenges-and-rules | N48: 2026-10-14 | P48: P052
A49: MyFundedPerps | Evaluation 1-Step Signature | size? [P053] | B49: verified | C49: static | F49: 6 | G49: NONE | H49: TRUE | L49: dll_usd(pct_of_start);max_contracts;start_balance;touch_after_lock_not_modeled | M49: https://docs.myfundedperpetuals.com/guides/challenges-and-rules | N49: 2026-10-14 | P49: P053
A50: MyFundedPerps | Evaluation Elite 3% DLL | size? [P054] | B50: verified | C50: static | F50: 5 | G50: NONE | H50: TRUE | L50: dll_usd(pct_of_start,optional);max_contracts;start_balance | M50: https://docs.myfundedperpetuals.com/guides/challenges-and-rules | N50: 2026-10-14 | P50: P054
A51: MyFundedPerps | Evaluation Elite No DLL | size? [P055] | B51: verified | C51: static | F51: 5 | G51: NONE | H51: TRUE | I51: NONE | L51: max_contracts;start_balance | M51: https://docs.myfundedperpetuals.com/guides/challenges-and-rules | N51: 2026-10-14 | P51: P055
A52: Manual | B52: manual | L52: all

Sheet Contracts
A1: symbol | B1: name | C1: tick_size | D1: tick_value_usd | E1: status | F1: checked_date | G1: source_url | H1: note
A2: MES | B2: Micro E-mini S&P 500 | C2: 0.25 | D2: 1.25 | E2: verified_indirect | F2: 2026-10-14 | G2: https://www.cmegroup.com/articles/faqs/micro-e-mini-equity-index-futures-frequently-asked-questions.html | H2: Direct fetch of the cmegroup.com page returned HTTP 403/500 (bot-blocked); values read from the search-index copy of the cited CME Group page. Re-verify in a browser before release. CME FAQ table: 0.25 index points = $1.25; contract page: $5 x index, 0.25 tick.
A3: MNQ | B3: Micro E-mini Nasdaq-100 | C3: 0.25 | D3: 0.50 | E3: verified_indirect | F3: 2026-10-14 | G3: https://www.cmegroup.com/articles/faqs/micro-e-mini-equity-index-futures-frequently-asked-questions.html | H3: Direct fetch of the cmegroup.com page returned HTTP 403/500 (bot-blocked); values read from the search-index copy of the cited CME Group page. Re-verify in a browser before release. CME FAQ table: 0.25 index points = $0.50.
A4: ES | B4: E-mini S&P 500 | C4: 0.25 | D4: 12.50 | E4: flagged | F4: 2026-10-14 | G4: https://www.cmegroup.com/markets/equities/sp/e-mini-sandp500.contractSpecs.html | H4: Direct fetch of the cmegroup.com page returned HTTP 403/500 (bot-blocked); values read from the search-index copy of the cited CME Group page. Re-verify in a browser before release. CME excerpt seen did not show the tick/multiplier text; 0.25 x $50 = $12.50 confirmed only by third-party (barchart). FLAG: needs direct check of CME page.
A5: NQ | B5: E-mini Nasdaq-100 | C5: 0.25 | D5: 5.00 | E5: verified_indirect | F5: 2026-10-14 | G5: https://www.cmegroup.com/trading/equity-index/files/emini-nasdaq-100-futures-options.pdf | H5: Direct fetch of the cmegroup.com page returned HTTP 403/500 (bot-blocked); values read from the search-index copy of the cited CME Group page. Re-verify in a browser before release. CME fact sheet: outrights 0.25 index points = $5.00; contract page: $20 x index.
A6: GC | B6: Gold (COMEX) | C6: 0.10 | D6: 10.00 | E6: verified_indirect | F6: 2026-10-14 | G6: https://www.cmegroup.com/market-regulation/files/gold-futures-and-options-fact-card.pdf | H6: Direct fetch of the cmegroup.com page returned HTTP 403/500 (bot-blocked); values read from the search-index copy of the cited CME Group page. Re-verify in a browser before release. CME fact card: 100 troy oz, $0.10/oz; tick value derived 100 x 0.10 = $10.00 (CME education page states $10.00 tick).
A7: MGC | B7: Micro Gold (COMEX) | C7: 0.10 | D7: 1.00 | E7: verified_indirect | F7: 2026-10-14 | G7: https://www.cmegroup.com/rulebook/COMEX/1a/120.pdf | H7: Direct fetch of the cmegroup.com page returned HTTP 403/500 (bot-blocked); values read from the search-index copy of the cited CME Group page. Re-verify in a browser before release. Rulebook ch.120: 10 troy oz, $0.10/oz; derived 10 x 0.10 = $1.00 (CME education page states $1.00).
A8: CL | B8: Light Sweet Crude Oil (NYMEX) | C8: 0.01 | D8: 10.00 | E8: verified_indirect | F8: 2026-10-14 | G8: https://www.cmegroup.com/rulebook/NYMEX/2/200.pdf | H8: Direct fetch of the cmegroup.com page returned HTTP 403/500 (bot-blocked); values read from the search-index copy of the cited CME Group page. Re-verify in a browser before release. Rulebook ch.200: 1,000 bbl, $0.01/bbl; derived 1000 x 0.01 = $10.00.
A9: MCL | B9: Micro WTI Crude Oil (NYMEX) | C9: 0.01 | D9: 1.00 | E9: flagged | F9: 2026-10-14 | G9: https://www.cmegroup.com/markets/energy/files/getting-started-with-micro-wti-crude-oil-options.pdf | H9: Direct fetch of the cmegroup.com page returned HTTP 403/500 (bot-blocked); values read from the search-index copy of the cited CME Group page. Re-verify in a browser before release. CME doc shows 100 bbl and $0.01/bbl but is the OPTIONS guide; futures contract-spec page not read. Derived 100 x 0.01 = $1.00. FLAG.
A10: 6E | B10: Euro FX | C10: 0.00005 | D10: 6.25 | E10: verified_indirect | F10: 2026-10-14 | G10: https://www.cmegroup.com/markets/fx/fx-product-guide.html | H10: Direct fetch of the cmegroup.com page returned HTTP 403/500 (bot-blocked); values read from the search-index copy of the cited CME Group page. Re-verify in a browser before release. CME FX product guide: 125,000 EUR, outright tick 0.00005; derived 125000 x 0.00005 = $6.25.
A11: M6E | B11: Micro EUR/USD | C11: 0.0001 | D11: 1.25 | E11: verified_indirect | F11: 2026-10-14 | G11: https://www.cmegroup.com/markets/microsuite/fx.html | H11: Direct fetch of the cmegroup.com page returned HTTP 403/500 (bot-blocked); values read from the search-index copy of the cited CME Group page. Re-verify in a browser before release. CME Micro FX page: 12,500 EUR, 0.0001, value of one tick $1.25.
A13: All tick values verified indirectly (CME pages bot-blocked); confirm on cmegroup.com. 'flagged' rows need a direct check.
